Workbook

Sheet Summary
A1: QuantumTech HotSpot Investment Universe Database
A3: Key Entitiyes & Modalities
A5: Top Quantum Computing Companies | N5: Top Quantum Cyber Security Companies
A6: Type | B6: Count | N6: Type | O6: Count
A7: Public Companies | B7: 10 | N7: Public Companies | O7: 8
A8: Promising IPO | B8: 9 | N8: Promising IPO | O8: 8
A9: Top Pre-IPO | B9: 10 | N9: Top Pre-IPO | O9: 10
A10: Promising Pre-IPO | B10: 10 | N10: Promising Pre-IPO | O10: 9
A11: Total | B11: =SUM(B7:B10) -> 39 | N11: Total | O11: =SUM(O7:O10) -> 35
A18: Top Quantum Computing Companies | N18: Investors by HotSpot
A19: Type | B19: Count | N19: HotSpot | O19: Count
A20: Public Companies | B20: 7 | N20: Quantum Computing | O20: 193
A21: Promising Pre-IPO | B21: 9 | N21: Cyber Security HotSpot | O21: 196
A22: Pre IPO Companies | B22: 9 | N22: Communications HotSpot | O22: 175
A23: Post Ipo Companies | B23: 7 | N23: Total | O23: =SUM(O20:O22) -> 564
A24: Total | B24: =SUM(B20:B23) -> 32
A30: Companies UDMs by HotSpot | N30: Investors UDMs by HotSpot
A31: HotSpot | B31: Count | N31: HotSpot | O31: Count
A32: Quantum Computing | B32: 101 | N32: Quantum Computing | O32: 570
A33: Cyber Security HotSpot | B33: 93 | N33: Cyber Security HotSpot | O33: 522
A34: Communications HotSpot | B34: 87 | N34: Communications HotSpot | O34: 420
A35: Total | B35: =SUM(B32:B34) -> 281 | N35: Total | O35: =SUM(O32:O34) -> 1512
A41: QuantumTech HotSpot Investment Universe Database
A42: Key Entitiyes & Modalities
A44: Quantum Bio & Medicine Companies | N44: Quantum Materials & NanoTech Companies
A45: Type | B45: Count | N45: Type | O45: Count
A46: Promising Private Companies | B46: 6 | N46: Promising Private Companies | O46: 6
A47: Pre IPO Companies | B47: 4 | N47: Pre IPO Companies | O47: 4
A48: Post IPO Companies | B48: 5 | N48: Post IPO Companies | O48: 4
A49: Public Companies | B49: 6 | N49: Public Companies | O49: 6
A50: Total | B50: =SUM(B46:B49) -> 21 | N50: Total | O50: =SUM(O46:O49) -> 20
A57: Quantum AI & ML Companies | N57: Investors
A58: Type | B58: Count | N58: HotSpot | O58: Count
A59: Promising Private Companies | B59: 6 | N59: Quantum Bio & Medicine | O59: 39
A60: Pre IPO Companies | B60: 4 | N60: Quantum Materials & NanoTech | O60: 51
A61: Post IPO Companies | B61: 5 | N61: Quantum AI & ML | O61: 50
A62: Public Companies | B62: 4 | N62: Total | O62: =SUM(O59:O61) -> 140
A63: Total | B63: =SUM(B59:B62) -> 19
A69: Companies UDMs | N69: Investors UDMs
A70: HotSpot | B70: Count | N70: HotSpot | O70: Count
A71: Quantum Bio & Medicine | B71: 40 | N71: Quantum Bio & Medicine | O71: 68
A72: Quantum Materials & NanoTech | B72: 66 | N72: Quantum Materials & NanoTech | O72: 84
A73: Quantum AI & ML | B73: 51 | N73: Quantum AI & ML | O73: 87
A74: Total | B74: =SUM(B71:B73) -> 157 | N74: Total | O74: =SUM(O71:O73) -> 239

Sheet Quantum Bio & Medicine 
A1: segment | B1: name | C1: Logo | D1: description | E1: short description | F1: website | G1: founded on | H1: num_employees_enum | I1: twitter | J1: facebook | K1: linkedin | L1: investors | M1: stock symbol | N1: went public on | O1: categories | P1: category groups | Q1: locations | R1: city | S1: region | T1: country | U1: founders | V1: contact email
A2: Promising Private Companies | B2: Algorithmiq | C2: Algorithmiq.png | D2: Algorithmiq develops algorithms to solve currently inaccessible problems in life sciences. The company utilizes its expertise in quantum information, complex systems, and computational physics to develop algorithms to develop new and effective drugs, solve problems in life sciences, and discover new materials. | E2: Algorithmiq develops algorithms to solve currently inaccessible problems in life sciences. | F2: https://algorithmiq.fi | G2: 2020 | K2: https://www.linkedin.com/company/algorithmiq | L2: European Investment Bank,Tiger Global Management,K5 Global,Inventure,Tesi | O2: Biotechnology,Life Science,Market Research,Quantum Computing | Q2: Turku,Western Finland,Finland,Europe | R2: Turku | S2: Western Finland | T2: Finland | U2: Boris Sokolov,Guillermo GarciaPerez,Matteo Rossi,Sabrina Maniscalco | V2: info@algorithmiq.fi
B3: Polaris Quantum Biotech | C3: Polaris Quantum Biotech.png | D3: Polaris Quantum Biotech is revolutionizing drug design by combining quantum computing with artificial intelligence and precision medicine. By unifying these technologies, the company is able to search massive chemical libraries, identifying potential drugs that target proteins for specific disease modulations. The company was founded in 2020 and is headquartered in Durham, North Carolina. | E3: Polaris Quantum Biotech revolutionizes drug design by joining quantum computing with AI and precision medicine. | F3: https://www.polarisqb.com/ | G3: 2020 | I3: https://x.com/polarisqb | K3: https://www.linkedin.com/company/polarisqb/ | L3: OurCrowd,Infinity Medical | O3: Artificial Intelligence (AI),Biotechnology,Health Care,Precision Medicine,Quantum Computing | Q3: Durham,North Carolina,United States,North America | R3: Durham | S3: North Carolina | T3: United States | U3: Bill Shipman,Shahar Keinan | V3: info@polarisqb.com
B4: Menten AI | C4: Menten AI.png | D4: Menten AI designs new protein drugs and enzymes using quantum computers and machine learning. Proteins are large molecules that can twist into many shapes. Discovering the right shape for a protein to be a drug or a biocatalyst among almost endless possibilities is a major challenge. Menten AI solves this problem by using machine learning and quantum computing to find better starting points for discovery and further development. Quantum computing makes it possible to represent multiple states of the protein simultaneously and efficiently find the best designs. The team created the world’s first peptide designed on a quantum computer and is now working on peptide therapeutics for oncology and neurodegeneration, as well as on enzymes for industrial applications. | E4: Menten AI develops peptide and protein therapeutics using machine learning and quantum computing. | F4: http://menten.ai/ | G4: 2018 | I4: https://x.com/menten_ai | K4: https://www.linkedin.com/company/mentenai/ | L4: Alumni Ventures,Khosla Ventures,Y Combinator,Uncork Capital,Creative Destruction Lab (CDL) | O4: Artificial Intelligence (AI),Biotechnology,Chemical,Health Care,Life Science,Machine Learning,Pharmaceutical,Quantum Computing,Therapeutics | Q4: Palo Alto,California,United States,North America | R4: Palo Alto | S4: California | T4: United States | U4: Hans Melo,Tamas Gorbe,Vikram K. Mulligan | V4: info@menten.ai
B5: Qubit Pharmaceuticals | C5: Qubit Pharmaceuticals.png | D5: Qubit Pharmaceuticals is a brandnew international company based in Paris that was founded by CNAM, CNRS, the University of Texas at Austin, the Sorbonne University, and Washington University. Qubit Pharmaceuticals is built on more than 20 years of R and D that has been recognized with the most prestigious awards. It was founded by Pr Jay Ponder, Pr Pengyu Ren, Pr J.P. Piquemal, Dr Louis Lagardere, and Pr Matthieu Montes. | E5: Qubit Pharmaceuticals is an EIT Health Headstart laureate and is incubated at Paris Biotech Santé. | F5: https://www.qubitpharmaceuticals.com | G5: 2020 | H5: 51-100 | K5: https://www.linkedin.com/company/qubitpharmaceuticals | L5: Quantonation,XAnge,Omnes Capital,European Innovation Council,Octave Klaba | O5: Biotechnology | Q5: Paris,IledeFrance,France,Europe | R5: Paris | S5: IledeFrance | T5: France | U5: Jay Ponder,Jean Philip Piquemal,Matthieu Montes
B6: Quomics | C6: Quomics.png | D6: Q‑omics is an AI‑powered multi‑omics intelligence platform that helps life‑science and biotech organizations analyze and integrate complex genomic, transcriptomic, proteomic, and metabolomic data for drug discovery, precision medicine, and translational research. | E6: AI‑driven multi‑omics analytics platform for life‑science R&D. | F6: https://qomics.ai | G6: 2024 | H6: 1–10 | O6: multi‑omics, AI, genomics, bioinformatics, drug discovery | P6: healthtech, biotech, AI / data‑analytics | Q6: Seoul (registered in Republic of Korea) | R6: Seoul | T6: Republic of Korea | U6: SukJoon Yoon | V6: qomics.io@gmail.com
B7: QuantumDance | C7: QuantumDance.png | D7: QuantumDance Technologies applies quantum‑inspired and quantum‑AI algorithms to large‑scale biological data, including medical imaging, multi‑omics, and clinical datasets, to accelerate drug discovery, improve diagnostic accuracy, and identify novel biomarkers for healthcare providers and pharma companies. | E7: Quantum‑AI engine for healthcare and multi‑omics. | F7: https://quantumdance.io | H7: 1–10 | O7: quantum‑AI, healthcare AI, medical imaging, multi‑omics, drug discovery, biomarker discovery | P7: healthtech, AI, quantum computing for medicine | Q7: (remote / distributed) | T7: United States
A8: Pre IPO Companies | B8: Quantinuum | C8: Quantinuum.png | D8: Quantinuum is a quantum company dedicated to the advancement of quantum computers and the development of software solutions. Quantinuum's technology spearheads advancements in materials discovery, cybersecurity, and nextgeneration quantum AI. The company has nearly 500 professionals, including over 370 scientists and engineers, Quantinuum takes the helm in driving the quantum computing revolution globally. | E8: Quantinuum is a IT firm that accelerates quantum computing and the development of applications across chemistry, cybersecurity, and finance. | F8: https://www.quantinuum.com | G8: 2021 | H8: 501-1000 | I8: https://x.com/QuantinuumQC | J8: https://www.facebook.com/QuantinuumQC | K8: https://www.linkedin.com/company/quantinuumqc | L8: QED Investors,NVentures,Amgen,JP Morgan Chase,Korea Investment Partners | O8: Cyber Security,Quantum Computing,Software Engineering | Q8: Broomfield,Colorado,United States,North America | R8: Broomfield | S8: Colorado | T8: United States | U8: Ilyas Khan | V8: info@quantinuum.com
B9: SandboxAQ | C9: SandboxAQ.png | D9: SandboxAQ develops AI and quantum technology products aimed at solving complex challenges. The company integrates knowledge from various fields to create Large Quantitative Models and AI sensing applications. Its focus is on providing practical solutions in areas that require advanced computational techniques. The industries served include financial services, healthcare, and telecommunications. | E9: SandboxAQ develops AI and quantum technology solutions that enhance biopharma, cybersecurity, and materials science. | F9: https://www.sandboxaq.com | G9: 2016 | H9: 101-250 | I9: https://x.com/sandboxaq | K9: https://www.linkedin.com/company/sandboxaq | L9: NVIDIA,Paladin Capital Group,BNP Paribas,S32,US Innovative Technology Fund | O9: Artificial Intelligence (AI),Cyber Security,Information Technology,Quantum Computing,SaaS | Q9: Palo Alto,California,United States,North America | R9: Palo Alto | S9: California | T9: United States | U9: Jack Hidary | V9: info@sandboxaq.com
B10: Pasqal | C10: Pasqal.png | D10: PASQAL is developing a fullstack quantum computer that will be used to simulate complex phenomena for scientific discovery and to address general problems such as optimization, drug discovery, and machine learning. The company's quantum processing units are made up of hundreds of atomic qubits in 2D and 3D arrays, and their programming environment, to address our customers' needs in quantum computing and simulation. | E10: Pasqal develops neutral atombased quantum processors, simulators, and computers. | F10: https://www.pasqal.com | G10: 2019 | H10: 251-500 | I10: https://x.com/pasqal_quantum | J10: https://www.facebook.com/Pasqal.quantum.computing | K10: https://www.linkedin.com/company/pasqal | L10: Bpifrance,Temasek Holdings,Daphni,Quantonation,European Innovation Council | O10: Computer,Information Technology,Quantum Computing,Simulation | Q10: Palaiseau,IledeFrance,France,Europe | R10: Palaiseau | S10: IledeFrance | T10: France | U10: Alain Aspect,Antoine Browaeys,Christophe Jurczak,GeorgesOlivier Reymond,Thierry Lahaye | V10: nicolas.proust@pasqal.com
B11: QuEra | C11: QuEra.png | D11: QuEra is a software company specializing in cloud based SaaS data collection and automation solutions for healthcare, specifically mental health. With QuEra software data collection and analysis processes are streamlined and overhead eliminated. They provide solutions for clinical psychologists and other mental professionals to digitize self assessment questionnaires and other psychometric instruments. The entire process from data collection, scoring, processing and storage becomes digital eliminating overhead, errors and improving outcomes and reliability | E11: SaaS company for healthcare data collection and automated systems | F11: https://quera.io | G11: 2007 | I11: https://x.com/Quera34731567 | J11: https://www.facebook.com/quera.io | K11: https://www.linkedin.com/company/queraio | O11: Data Collection and Labeling,Electronic Health Record (EHR),Health Care,Information Technology,Personal Health,SaaS,Software | Q11: Reykjavík,Gullbringusysla,Iceland,Europe | R11: Reykjavík | S11: Gullbringusysla | T11: Iceland | V11: hello@quera.io
A12: Post IPO Companies | B12: D-Wave Quantum | C12: D-Wave Quantum.png | D12: DWave provides development and delivery of quantum computing systems, software and services, and is the world’s first commercial supplier of quantum computers—and the only company building both annealing quantum computers and gatemodel quantum computers. Our mission is to unlock the power of quantum computing today to benefit business and society. | E12: DWave Systems designs and manufactures quantum computing and superconducting electronics. | F12: https://www.dwavequantum.com | G12: 1999 | H12: 101-250 | I12: https://x.com/dwavesys | J12: https://www.facebook.com/dwavesys | K12: http://www.linkedin.com/company/dwavesystemsinc. | L12: Business Development Bank of Canada,Goldman Sachs,Fidelity,Government of Canada,SCALE AI | M12: QBTS | N12: 20220808 | O12: Electronics,Manufacturing,Quantum Computing,Semiconductor | Q12: Palo Alto,California,United States,North America | R12: Palo Alto | S12: California | T12: United States | U12: Eric Ladizinsky,Geordie Rose | V12: info@dwavesys.com
B13: Rigetti Computing | C13: Rigetti Computing.png | D13: Rigetti Computing is a fullstack quantum computing company. It designs and manufactures quantumintegrated circuits. It packages and deploys those chips in a lowtemperature environment, and they build control systems to perform quantum logic operations on them. The company develops software to integrate its systems directly into existing cloud infrastructure. It has also developed new algorithms for quantum computing, with a focus on nearterm applications in computational chemistry and machine learning. Our product, Forest, is the world’s first fullstack programming and execution environment for quantum/classical computing. | E13: Rigetti Computing is a quantum computing company that builds and deploys fullstack quantum systems with superconducting qubits. | F13: http://www.rigetti.com | G13: 2013 | H13: 101-250 | I13: https://x.com/rigetti | J13: https://www.facebook.com/rigetticomputing | K13: https://www.linkedin.com/company/rigetticomputing | L13: Andreessen Horowitz,Franklin Templeton,Alumni Ventures,Bessemer Venture Partners,Felicis | M13: RGTI | N13: 20220302 | O13: AI Infrastructure,Artificial Intelligence (AI),Big Data,Hardware,Quantum Computing,Semiconductor,Software | Q13: Berkeley,California,United States,North America | R13: Berkeley | S13: California | T13: United States | U13: Chad Rigetti,Spencer Rascoff | V13: info@rigetti.com
B14: IonQ | C14: IonQ.png | D14: IONQ develops generalpurpose quantum information processor using a trapped ion approach. The method enables qubit replication optical networkability, and optimized algorithms to support scalable quantum computing. | E14: IONQ offers enterprisegrade quantum systems designed for businesses seeking to harness the power of quantum computing in their operations. | F14: https://ionq.com | G14: 2015 | H14: 251-500 | I14: https://x.com/IonQ_Inc | J14: https://www.facebook.com/profile.php?id=100068180767172 | K14: https://www.linkedin.com/company/ionq.co | L14: Bosch Ventures,Lockheed Martin Ventures,Fidelity,New Enterprise Associates,OUP (Osage University Partners) | M14: DMYT | N14: 20200220 | O14: Computer,Electronics,Finance,Information Services,Information Technology,Mobile Apps,Quantum Computing,Software | Q14: College Park,Maryland,United States,North America | R14: College Park | S14: Maryland | T14: United States | U14: Christopher Monroe,Jungsang Kim,Niccolo de Masi | V14: info@ionq.com
B15: XtalPi | C15: XtalPi.png | D15: XtalPi is a pharmaceutical technology company that is reinventing the industry’s approach to drug research and development with its Intelligent Digital Drug Discovery and Development (ID4) platform. Through its tightly interwoven quantum mechanics, artificial intelligence, and highperformance cloud computing algorithms, the ID4 platform enables pharmaceutical companies to increase their efficiency, accuracy, and success rate at critical stages of drug R&D. By accelerating the pace of drug discovery and development, XtalPi aims to contribute to a healthier society worldwide. Founded in 2014 by a group of quantum physicists at MIT, XtalPi has since grown into an elite team of researchers with multidisciplinary expertise in physics, chemistry, pharmaceutical R&D, and algorithm design. XtalPi has received much recognition for its cuttingedge technologies, its innovative solutions, and the breadth of potential applications of its offerings across the pharmaceutical value chain, which has allowed it to gain industry approval and establish strategic partnerships with several top international pharmaceutical companies. | E15: XtalPi is a pharmaceutical technology company that is reinventing drug discovery by enabling dry lab predictions with wet lab validation. | F15: http://www.xtalpi.com/ | G15: 2015 | H15: 501-1000 | I15: https://x.com/xtalpi | K15: https://www.linkedin.com/company/xtalpi/ | L15: HSG,Tencent,OrbiMed,Shunwei Capital,Alphabet | M15: 2228 | N15: 20240613 | O15: Artificial Intelligence (AI),Biotechnology,Pharmaceutical | Q15: Shenzhen,Guangdong,China,Asia | R15: Shenzhen | S15: Guangdong | T15: China | U15: Jian Ma,Lipeng Lai,Shuhao Wen | V15: contact@xtalpi.com
B16: Zapata AI | C16: Zapata AI.png | E16: Zapata AI builds operational support platforms for enterprise solutions using augmented intelligence and machine learning. | F16: https://zapataai.com | G16: 2018 | O16: Artificial Intelligence (AI),Augmented Reality,Machine Learning,Software | Q16: Augusta,Georgia,United States,North America | R16: Augusta | S16: Georgia | T16: United States | V16: mediainquiries@zapataai.com
A17: Public Companies | B17: NVIDIA | C17: NVIDIA.png | D17: NVIDIA is a computing platform company innovating at the intersection of graphics, HPC and AI. The company specialises in the manufacture of graphics processor technologies for workstations, desktop computers, and mobile devices. The company is a major supplier of integrated circuits used for personal computer motherboard chipsets, graphics processing units (GPUs), and game consoles. | E17: NVIDIA is a computing platform company operating at the intersection of graphics, HPC, and AI. | F17: https://www.nvidia.com | G17: 1993 | H17: 10001+ | I17: https://x.com/nvidia | J17: https://www.facebook.com/NVIDIA.AP | K17: https://www.linkedin.com/company/nvidia | L17: Sequoia Capital,SoftBank Vision Fund,ARK Investment Management,DARPA,TriplePoint Capital | M17: NVDA | N17: 19990122 | O17: AI Infrastructure,Artificial Intelligence (AI),Consumer Electronics,Foundational AI,GPU,Hardware,Software,Virtual Reality | Q17: Santa Clara,California,United States,North America | R17: Santa Clara | S17: California | T17: United States | U17: Chris Malachowsky,Curtis Priem,Jensen Huang | V17: info@nvidia.com
B18: IBM | C18: IBM.png | D18: IBM is a technology and innovation company that offers a wide range of technology and consulting services; a broad portfolio of middleware for collaboration, predictive analytics, software development, and systems management. It offers services across AI, machine learning, cybersecurity, analytics, DevOps, and more, helping businesses innovate and automate processes. | E18: IBM is an IT technology and consulting firm providing computer hardware, software, infrastructure, and hosting services. | F18: http://www.ibm.com | G18: 1911 | H18: 10001+ | I18: https://x.com/IBM | J18: https://www.facebook.com/IBM | K18: https://www.linkedin.com/company/ibm | M18: IBM | N18: 19780113 | O18: Business Development,Business Information Systems,CRM,Data Management,Foundational AI,Software | Q18: Armonk,New York,United States,North America | R18: Armonk | S18: New York | T18: United States | U18: Gerard Aldus,Thomas J. Watson | V18: ews@us.ibm.com
B19: AstraZeneca | C19: AstraZeneca.png | D19: AstraZeneca is a biopharmaceutical company specializing in the discovery, development, manufacturing, and marketing of prescription medicines that make a meaningful difference in healthcare. It discovers new medicines that are designed to improve the health and quality of life of patients, offering added benefits such as reduced side effects or better ways of taking the treatment. It focuses on getting the best from every medicine it makes by exploring all the ways it can be used or improved. | E19: AstraZeneca is a pharmaceutical company that discovers, develops, manufactures, and markets prescription medicines. | F19: https://www.astrazeneca.com | G19: 1913 | H19: 10001+ | I19: https://x.com/astrazeneca | J19: https://www.facebook.com/astrazenecacareers | K19: http://www.linkedin.com/company/astrazeneca | M19: AZN | N19: 19930601 | O19: Biopharma,Biotechnology,Health Care,Medical,Pharmaceutical,Precision Medicine | Q19: Cambridge,Cambridgeshire,United Kingdom,Europe | R19: Cambridge | S19: Cambridgeshire | T19: United Kingdom
B20: Bayer | C20: Bayer.png | D20: Bayer is an enterprise with core competencies in the life science fields of healthcare and nutrition. They design their products and services to help people and the planet thrive by supporting efforts to address unprecedented challenges. Their businesses include pharmaceuticals, consumer health, and crop science. They focus on developing and commercializing products and solutions based on scientific knowledge. | E20: Bayer is a life science company that specializes in the areas of health care and agriculture. | F20: https://www.bayer.com | G20: 1863 | H20: 10001+ | I20: https://x.com/bayer | J20: http://www.facebook.com/Bayer | K20: https://www.linkedin.com/company/bayer | L20: Bill & Melinda Gates Foundation,Temasek Holdings,Bank of America | M20: BAYN | N20: 20091002 | O20: Biotechnology,Chemical,Health Care,Life Science,Pharmaceutical | Q20: Leverkusen,NordrheinWestfalen,Germany,Europe | R20: Leverkusen | S20: NordrheinWestfalen | T20: Germany | U20: Friedrich Bayer,Johann Friedrich Weskott | V20: info@bayer.com
B21: Alphabet (Google) | C21: Alphabet (Google).png | D21: Alphabet is a holding company that provides projects with resources, freedom, and focus to make their ideas happen. Alphabet is the holding company for Google and several Google entities, including Google X, Google Ventures, Google Capital, Calico, and its Life Sciences efforts. The company's CEO, Larry Page announced the operational restructuring effort for Alphabet Inc. to replace Google Inc. as the official publiclytraded entity. He announced that all shares of Google would automatically convert into the same number of shares of Alphabet, with all of the same rights. The two classes of shares will continue to trade on Nasdaq as GOOGL and GOOG. | E21: Alphabet is a holding company that provides projects with resources, freedom, and focus to make their ideas happen. | F21: https://abc.xyz | G21: 2015 | H21: 10001+ | I21: https://x.com/alphabetlnc | J21: https://www.facebook.com/alphabetxyz | K21: https://www.linkedin.com/company/alphabetinc | M21: GOOGL | N21: 20040819 | O21: Artificial Intelligence (AI),Information Technology,Search Engine,Software,Video Streaming | Q21: Mountain View,California,United States,North America | R21: Mountain View | S21: California | T21: United States | U21: Larry Page,Sergey Brin
B22: Merck KGaA | C22: Merck KGaA.png | D22: Merck (d.b.a. EMD Millipore in the U.S. and Canada) is a German chemical and pharmaceutical company. Merck, also known as “German Merck” and “Merck Darmstadt”, was founded in Darmstadt, Germany, in 1668, making it the world's oldest operating chemical and pharmaceutical company. The company was privately owned until going public in 1995. However, the Merck family still controls a majority (≈70%) of the company's shares. Following World War I, Merck lost possession of its foreign sites, including the Merck & Co. subsidiary in the United States. Merck & Co., which operates as Merck Sharp and Dohme (MSD) outside the U.S. and Canada, is now an independent company. Merck KGaA operates mainly in Europe, Africa, Asia, Oceania and Latin America. Since Merck & Co. holds the rights to the Merck name in the U.S. and Canada, the company operated under the umbrella brand EMD Chemicals in North America, and since 2010 as EMD Millipore (after the acquisition of Millipore Corporation), formed from the initials of Emanuel Merck, Darmstadt. Founded in 1668 in Darmstadt, Merck KGaA of Darmstadt, Germany, is the world's oldest pharmaceutical and chemical company. The success of the export business to the United States led in 1887 to the establishment of an office in New York, which gave rise to their subsidiary [Merck & Co.](http://www.crunchbase.com/organization/merckcoinc) four years later. Owing to World War I, Merck & Co. was expropriated in 1917. The two companies have been separate every since. Merck KGaA Subsidiaries: [Merck Consumer Healthcare](http://www.crunchbase.com/organization/merckconsumerhealthcare) [Merck Performance Materials](http://www.crunchbase.com/organization/merckperformancematerials) | E22: Merck is a pharmaceutical and chemical enterprise that develops prescription drugs and overthecounter products. | F22: https://www.merckgroup.com | G22: 1668 | H22: 10001+ | I22: https://x.com/merckgroup | J22: https://www.facebook.com/MerckDeutschland | K22: https://www.linkedin.com/company/merckgroup | L22: Scottish Enterprise | M22: MRK | N22: 20020111 | O22: Biotechnology,Health Care,Life Science,Manufacturing,Pharmaceutical | Q22: Darmstadt,Hessen,Germany,Europe | R22: Darmstadt | S22: Hessen | T22: Germany | U22: Friedrich Merck | V22: service@merckgroup.com

Sheet Quantum Bio & Medicine UDMs
A1: Name | B1: Photo | C1: LinkedIn | D1: Followers | E1: Email | F1: Title | G1: Company | H1: Company Industry | I1: Company Website | J1: Company Linkedin | K1: Company Founded In | L1: Company Size | M1: Current Job Duration | N1: Country | O1: Location | P1: Languages | Q1: Publications | R1: Honors And Awards | S1: Patents | T1: Volunteer and Awards | U1: License and Certifications | V1: Work Experience | W1: Education | X1: LinkedIn Summary | Y1: Headline | Z1: Photo
A2: Stephan Kudlacek | B2: Stephan Kudlacek.png | C2: https://www.linkedin.com/in/stephankudlacek | D2: 527 | E2: stephan.kudlacek@menten.ai | F2: Associate Director Protein Design | G2: Menten AI | H2: Biotechnology Research | I2: http://menten.ai | J2: https://www.linkedin.com/company/menten-ai/ | L2: 2-10 | M2: 3 yrs 8 mos | N2: United States | O2: Katy, Texas | Q2: Title: Physiological temperatures reduce dimerization of dengue and Zika virus recombinant envelope proteins Source: Journal of Biological Chemistry Summary: Abstract The spread of dengue (DENV) and Zika virus (ZIKV) is a major public health concern. The primary target of antibodies (Abs) that neutralize DENV and ZIKV is the envelope (E) glycoprotein, and there is interest in using soluble recombinant E (sRecE) proteins as subunit vaccines. However, the most potent neutralizing antibodies against DENV and ZIKV recognize epitopes on the virion surface that span two or more E proteins. Therefore, to create effective DENV and ZIKV vaccines, presentation of these quaternary epitopes may be necessary. The sRecE proteins from DENV and ZIKV crystallize as native-like dimers, but studies in solution suggest that these dimers are marginally stable. To better understand the challenges associated with creating stable sRecE dimers, we characterized the thermostability of sRecE proteins from ZIKV and three DENV serotypes, DENV2–4. All four proteins irreversibly unfolded at moderate temperatures (46°C–53°C). At 23°C and low micromolar concentrations, DENV2 and ZIKV were primarily dimeric, and DENV3–4 were primarily monomeric, whereas at 37°C, all four proteins were predominantly monomeric. We further show that the dissociation constant for DENV2 dimerization is very temperature sensitive, ranging from <1 μM at 25°C to 50 μM at 41°C, due to a large exothermic enthalpy of binding of –79 kcal/mol. We also found that quaternary epitope Ab binding to DENV2–4 and ZIKV sRecE is reduced at 37°C. Our observation of reduced sRecE dimerization at physiological temperature highlights the need for stabilizing the dimer as part of its development as a subunit vaccine. URL: https://www.ncbi.nlm.nih.gov/m/pubmed/29678884/?i=1&from=physiological%20temperatures%20reduce%20dimerization Title: Virus-Enabled Biosensor for Human Serum Albumin Source: ACS Analytical Chemistry Summary: Abstract: The label-free detection of human serum albumin (HSA) in aqueous buffer is demonstrated using a simple, monolithic, two-electrode electrochemical biosensor. In this device, both millimeter-scale electrodes are coated with a thin layer of a composite containing M13 virus particles and the electronically conductive polymer poly(3,4-ethylenedioxy thiophene) or PEDOT. These virus particles, engineered to selectively bind HSA, serve as receptors in this biosensor. The resistance component of the electrical impedance, Zre, measured between these two electrodes provides electrical transduction of HSA binding to the virus-PEDOT film. The analysis of sample volumes as small as 50 μL is made possible using a microfluidic cell. Upon exposure to HSA, virus-PEDOT films show a prompt increase in Zre within 5 s and a stable Zre signal within 15 min. HSA concentrations in the range from 100 nM to 5 μM are detectable. Sensor-to-sensor reproducibility of the HSA measurement is characterized by a coefficient-of-variance (COV) ranging from 2% to 8% across this entire concentration range. In addition, virus-PEDOT sensors successfully detected HSA in synthetic urine solutions. URL: http://pubs.acs.org/doi/abs/10.1021/acs.analchem.6b04840 Title: Shear-Stress-Mediated Refolding of Proteins from Aggregates and Inclusion Bodies Source: ChemBioChem Summary: Recombinant protein overexpression of large proteins in bacteria often results in insoluble and misfolded proteins directed to inclusion bodies. We report the application of shear stress in micrometer-wide, thin fluid films to refold boiled hen egg white lysozyme, recombinant hen egg white lysozyme, and recombinant caveolin-1. Furthermore, the approach allowed refolding of a much larger protein, cAMP-dependent protein kinase A (PKA). The reported methods require only minutes, which is more than 100 times faster than conventional overnight dialysis. This rapid refolding technique could significantly shorten times, lower costs, and reduce waste streams associated with protein expression for a wide range of industrial and research applications. URL: http://onlinelibrary.wiley.com/doi/10.1002/cbic.201402427/abstract Title: Focused dengue vaccine development: outwitting nature's design Source: Pathogens and Disease, Volume 77, Issue 1, February 2019 Summary: The four DENV serotypes are mosquito-borne pathogens that belong to the Flavivirus genus. These viruses present a major global health burden, being endemic in over 120 countries, causing ∼390 million reported infections yearly, with clinical symptoms ranging from mild fever to severe and potentially fatal hemorrhagic syndromes. Development of a safe and efficacious DENV vaccine is challenging because of the need to induce immunity against all four serotypes simultaneously, as immunity against one serotype can potentially enhance disease caused by a heterotypic secondary infection. So far, live-virus particle-based vaccine approaches struggle with inducing protective tetravalent immunity, while recombinant subunit approaches that use the envelope protein (E) as the major antigen, are gaining promise in preclinical studies. However, E-based subunits require further development and characterization to be used as effective vaccine antigens against DENV. In this review, we will address the shortcomings of recombinant E-based antigens and will discuss potential solutions to enhance E-based subunit antigen immunogenicity and vaccine efficacy. URL: https://academic.oup.com/femspd/article/77/1/ftz003/5307883 | S2: Title: Amino acid mutations for stabilizing the E protein dimer from Dengue virus. Issuer: US Provisional Patent UNC File No. 20-0009 Issued On: Aug , 2019 Description: None Title: Method for improving protein functionality using vortexing fluid shear forces Issuer: US Issued On: None Description: None | V2: Title: Associate Director Protein Design Company: None Start At: None Ends At: None Location: None Description: None Title: Senior Scientist, Protein Design Company: None Start At: None Ends At: None Location: None Description: None Title: PhD Candidate - Graduate Research Assistant Company: None Start At: None Ends At: None Location: None Description: None Title: Biomedical Research Assistant Company: None Start At: None Ends At: None Location: None Description: None | W2: School: The University of North Carolina at Chapel Hill Degree: Doctor of Philosophy - PhD, Biochemistry and Biophysics Activities: None School: UC Irvine Degree: Bachelor of Science, Chemistry with Biochemistry Concentration Activities: None | X2: • Driven and effective leader with +11 years research experience in protein engineering and biochemistry • Expert in both experimental and computational protein, antibody & cyclic peptide engineering and design • Head of Protein Design department & hiring manager managing a group of up to 10 scientists & contractors. • Led and contributed to cross-functional work with departments and partners in fields outside of expertise. • Lead for 6 internal drug discovery programs, including academic collaborations & large biotech commercial partnerships resulting in compounds with nM potency & in vivo efficacy. • Program lead of the company's computational cyclic peptide generative design platform. • Worked with CROs on protein production, purification, protein biophysical assay development. • Experienced in budget & resource management including cloud computing (AWS, GCP & Azure). • Representative research experience: vaccine antigen design, antibody engineering, computational macromolecular design, cyclic peptide therapeutics • Supervised scientists, contractors, PhD students, and undergraduates from different fields of expertise. • Google scholar list of publications and patents: https://scholar.google.com/citations?hl=en&user=zSQ1NEQAAAAJ&view_op=list_works&sortby=pubdate Skills Summary: - Protein & Peptide Libraries – Mammalian, yeast and phage display for high throughput screening - Biochemistry: Protein expression – Antibodies & proteins in bacteria, yeast, & mammalian cells; Affinity and SEC protein purification; Cloning – Restriction and recombination-based and plasmid construction - Biophysics: Thermodynamics & Kinetic binding measurements, ELISA, Protein Analysis & Structure Determination; Software – Pymol, Phenix, Coot, CCP4 - Bioinformatics: Protein & Peptide modeling; Software – Rosetta, Amber, OpenMM, Pymol, VMD; Programming – Bash, Python; - Immunology: Antigen preparation, serum antibody analysis, epitope mapping - Communication: Business development partner discussions & presentations, investor discussions & presentations, performance reviews, hiring interviews, government and private grant proposals, research conference presentations. | Y2: Associate Director - Protein Design at Menten AI | Z2: Stephan_Kudlacek.png
A3: Stefano Mangini | B3: Stefano Mangini.png | C3: https://www.linkedin.com/in/stfnmangini | D3: 1876 | E3: stefano.mangini@algorithmiq.fi | F3: Researcher | G3: Algorithmiq | H3: Research | I3: https://www.algorithmiq.fi | J3: https://www.linkedin.com/company/algorithmiq/ | L3: 11-50 | M3: 3 yrs | N3: Finland | O3: Helsinki, Uusimaa | P3: Inglese, Italiano | T3: Title: Assistente all'organizzazione Start At: 2015 Ends At: Present Company: Trieste Mini Maker Faire Cause: Science_and_technology Description: None Title: Assistente all'organizzazione Start At: 2016 Ends At: Present Company: Trieste Mini Maker Faire Cause: Science_and_technology Description: None | U3: Name: IBM Quantum Challenge Authority: IBM Date: 2020-5 URL: https://linkedin.com/company/1009 Name: ECDL Authority: ICDL Europe Date: Unknown URL: https://linkedin.com/company/740915 | V3: Title: Researcher Company: None Start At: None Ends At: None Location: None Description: None Title: Postdoctoral Researcher Company: None Start At: None Ends At: None Location: None Description: None Title: Co-Founder Company: None Start At: None Ends At: None Location: None Description: None Title: PhD Student Company: None Start At: None Ends At: None Location: None Description: None Title: Teaching Assistant Company: None Start At: None Ends At: None Location: None Description: None Title: Teaching assistant Company: None Start At: None Ends At: None Location: None Description: None Title: Quantum Machine Learning Intern Company: None Start At: None Ends At: None Location: None Description: None Title: Mentee Company: None Start At: None Ends At: None Location: None Description: None Title: Internship Company: None Start At: None Ends At: None Location: None Description: None | X3: I am a Research Scientist at Algorithmiq and a PostDoctoral Researcher at the University of Helsinki, and my research focuses on Quantum Computing. Previously, I was a Ph.D. student in Theoretical Physics at the University of Pavia (Italy), where I explored topics in Quantum Computing, and Quantum Machine Learning in particular. Moving on to more serious stuff, I am an optimistic nihilist guy hoping to have a positive impact on the world and the earthlings 🌎. 🤝 Collaborative • 🌱 Vegan • 🗻 Hiker • 🤖 Tech , and many other things. | Y3: Researcher @ Algorithmiq | PostDoc @ University of Helsinki | Z3: Stefano_Mangini.png
A4: Hans Melo | B4: Hans Melo.png | C4: https://www.linkedin.com/in/hansmelo | D4: 3725 | E4: hans@menten.ai | F4: Co-Founder and CEO | G4: Menten AI | H4: Biotechnology Research | I4: http://menten.ai | J4: https://www.linkedin.com/company/menten-ai/ | L4: 2-10 | M4: 7 yrs 9 mos | N4: Sweden | O4: Stockholm, Stockholm County | P4: Chinese, English | Q4: Title: Designing Peptides on a Quantum Computer Source: biorXiv Summary: Here we describe our mapping of the protein design problem to the D-Wave quantum annealer. URL: https://www.biorxiv.org/content/biorxiv/early/2019/09/02/752485.full.pdf Title: Origins of emotional consciousness. Source: Behavioral and Brain Sciences / Volume 39 Summary: None URL: https://www.cambridge.org/core/journals/behavioral-and-brain-sciences/article/div-classtitleorigins-of-emotional-consciousnessdiv/4E8E8BE2FC646BD267725F8E44D26066 Title: Reward: A marketer’s guide to the biological basis of pleasure. In M. Cerf & M. Garcia (Eds). Consumer Neurosciences. Source: MIT Press. Summary: None URL: None Title: Hierarchical Brain Systems Support Multiple Representations of Valence and Mixed Affect. Source: Emotion Review. Summary: None URL: None Title: Imaging Genetics of Positive Psychology. In Genetics of Psychological Well-being. Ed. Michael Pluess. Source: Oxford University Press. Summary: None URL: https://global.oup.com/academic/product/genetics-of-psychological-well-being-9780199686674?cc=us&lang=en& Title: The Function of Positive Emotions in Exploration. Positive Neuroscience. Eds. Greene, Morrison, Seligman. Source: Oxford University Press. Summary: None URL: https://global.oup.com/academic/product/positive-neuroscience-9780199977925?cc=us&lang=en&# Title: Kumaran, D., Melo, H.L. (2013) Transitivity performance, relational hierarchy knowledge and awareness: Results of an instructional framing manipulation. Hippocampus. Source: Unknown Summary: None URL: None Title: Kumaran, D., Melo, H.L.,Duzel,E. (2012) The Amygdala supports Learning and Representation of Social Hierarchies in Humans. Neuron. Source: Unknown Summary: None URL: http://www.ncbi.nlm.nih.gov/pubmed/23141075 | T4: Title: Volunteer Start At: 12/2015 Ends At: Present Company: Hospice Toronto Cause: Social_services Description: None | U4: Name: MILA - Deep Learning Summer School 2017 Authority: Université de Montréal Date: 2017-6 URL: https://linkedin.com/company/166700 Name: Data Science Specialization (Online Coursework - Coursera 2013) Authority: The Johns Hopkins University Date: Unknown URL: https://linkedin.com/company/3528 | V4: Title: Co-Founder and CEO Company: None Start At: None Ends At: None Location: None Description: None Title: Deep Learning Engineer Company: None Start At: None Ends At: None Location: None Description: None Title: Researcher/University Lecturer Company: None Start At: None Ends At: None Location: None Description: None Title: International Purchasing Manager Company: None Start At: None Ends At: None Location: None Description: None Title: Decision Science Researcher Company: None Start At: None Ends At: None Location: None Description: None | W4: School: University of Toronto Degree: Doctor of Philosophy (Ph.D.), Computational Neuroscience (Reinforcement Learning) Activities: None School: UCL Degree: Master of Science (MSc), Cognitive and Decision Science Activities: None School: Louisiana State University Degree: Bachelor's Degree, Physics Activities: None | X4: Menten AI is a drug discovery company focused on designing peptides for conditions with high unmet medical need. We develop computational methods for protein design that leverage machine learning and quantum computing. I am interested in diverse applications of quantum computing and machine learning in health and social good. My expertise is in quantum optimization, reinforcement learning, and computer vision (Deep Learning - CNNs). My research interests at the moment are quantum machine learning, constrained programming, meta-learning, few-shot learning, GAN's in general, and biologically inspired models. I have a technical background in Computational Neuroscience, Machine Learning, and Physics. Aside from my research and entrepreneurial work, I also served as a Scientific Advisor for The Decision Lab. www.hansmelo.com | Y4: Co-Founder and CEO at Menten AI - We’re hiring! | Z4: Hans_Melo.png
A5: Boris Sokolov | B5: Boris Sokolov.png | C5: https://www.linkedin.com/in/boris-sokolov-7301a7205 | D5: 321 | E5: boris@algorithmiq.fi | F5: Lead Researcher, co-founder | G5: Algorithmiq | H5: Research | I5: https://www.algorithmiq.fi | J5: https://www.linkedin.com/company/algorithmiq/ | L5: 11-50 | M5: 5 yrs 4 mos | N5: Finland | O5: Helsinki, Uusimaa | V5: Title: Lead Researcher, co-founder Company: None Start At: None Ends At: None Location: None Description: None | W5: School: Turun yliopisto - University of Turku Degree: Doctor of Philosophy - PhD, Theoretical and Mathematical Physics Activities: None | Y5: Senior Researcher at Algorithmiq Oy | Z5: Boris_Sokolov.png
A6: Sabrina Maniscalco | B6: Sabrina Maniscalco.png | C6: https://www.linkedin.com/in/sabrina-maniscalco | D6: 5501 | E6: sabrina.maniscalco@algorithmiq.fi | F6: Co-founder and CEO | G6: Algorithmiq | H6: Research | I6: https://www.algorithmiq.fi | J6: https://www.linkedin.com/company/algorithmiq/ | L6: 11-50 | M6: 5 yrs 8 mos | N6: Finland | O6: Helsinki, Uusimaa | V6: Title: Co-founder and CEO Company: None Start At: None Ends At: None Location: None Description: None Title: Chief Executive Officer Company: None Start At: None Ends At: None Location: None Description: None Title: Professor of Quantum Information, Computing, and Logic Company: None Start At: None Ends At: None Location: None Description: None Title: Adjunct Professor Company: None Start At: None Ends At: None Location: None Description: None Title: Professor, Chair of Theoretical Physics Company: None Start At: None Ends At: None Location: None Description: None Title: Associate Professor Company: None Start At: None Ends At: None Location: None Description: None | Y6: Co-founder and CEO, Algorithmiq Ltd | Z6: Sabrina_Maniscalco.png
A7: Daniel Cavalcanti | B7: Daniel Cavalcanti.png | C7: https://www.linkedin.com/in/dani-cavalcanti | D7: 1461 | E7: daniel@algorithmiq.fi | F7: Lead Researcher | G7: Algorithmiq | H7: Research | I7: https://www.algorithmiq.fi | J7: https://www.linkedin.com/company/algorithmiq/ | L7: 11-50 | M7: 2 yrs 9 mos | N7: Spain | O7: Barcelona, Catalonia | P7: English, Portuguese | Q7: Title: Publications on quantum physics Source: Unknown Summary: I have published over 100 research articles in peer-reviewed journals such as Nature, Physical Review Letters, and Optica. See my publication list at https://scholar.google.com/citations?user=MeuusYcAAAAJ&hl=en URL: https://arxiv.org/search/quant-ph?searchtype=author&query=Cavalcanti%2C+D Title: Split, But Still attached Source: Science Summary: Invited perspective article written for Science. URL: http://science.sciencemag.org/content/360/6387/376.summary | V7: Title: Lead Researcher Company: None Start At: None Ends At: None Location: None Description: None Title: Senior Researcher | Brand and Communication Director Company: None Start At: None Ends At: None Location: None Description: None Title: Founder and Creative Director Company: None Start At: None Ends At: None Location: None Description: None Title: Associate Professor Company: None Start At: None Ends At: None Location: None Description: None Title: Senior Researcher Company: None Start At: None Ends At: None Location: None Description: None Title: Postdoctoral Fellow Company: None Start At: None Ends At: None Location: None Description: None Title: Postdoctoral Researcher Company: None Start At: None Ends At: None Location: None Description: None | W7: School: Universitat de Barcelona Degree: Doctor of Philosophy - PhD, Physics Activities: None School: Elisava School of Design and Engineering Degree: Summer school, Infography and visualisation of information Activities: None School: IDEP BARCELONA Escuela Superior de Imagen y Diseño (UAO) Degree: Postgraduate course, Graphic Design Activities: None School: IDEP BARCELONA Escuela Superior de Imagen y Diseño (UAO) Degree: Master of Arts - MA, Graphic Design Activities: None School: Universidade Federal de Minas Gerais Degree: Master of Science - MS, Physics Activities: None School: Universidade Federal de Minas Gerais Degree: Bachelor's degree, Physics Activities: None | X7: I am a quantum physicist with over 15 years of post-PhD experience in both academia and industry, and a proven track record of advancing the frontiers of quantum technologies. My research contributions span more than 100 peer-reviewed publications, covering fundamental aspects of quantum information, quantum measurements, and computational methods. Currently, I serve as a Senior Scientist at Algorithmiq, where I lead a research group focused on the development of advanced quantum measurement techniques and their integration with high-performance computing (HPC). My work bridges theory and application, driving innovations that enable scalable quantum software solutions and accelerate the path toward practical quantum advantage. In addition to my scientific career, I am also a trained graphic designer, with a strong belief in the importance of scientific and technological communication. I value clarity, accessibility, and creativity in how complex ideas are shared with diverse audiences. | Y7: Lead Quantum Information Researcher | Z7: Daniel_Cavalcanti.png
A8: Nathalie Wuylens | C8: https://www.linkedin.com/in/nathalie-wuylens-6687b38 | D8: 375 | E8: nathalie.wuylens@qubit-pharmaceuticals.com | F8: Directrice générale déléguée | G8: Qubit Pharmaceuticals | H8: Software Development | I8: https://www.qubit-pharmaceuticals.com | J8: https://www.linkedin.com/company/qubit-pharmaceuticals/ | L8: 51-200 | M8: 2 yrs | N8: France | O8: Paris, Île-de-France | V8: Title: Directrice générale déléguée Company: None Start At: None Ends At: None Location: None Description: None Title: Directrice Juridique / Legal Director Company: None Start At: None Ends At: None Location: None Description: None Title: Director of legal affairs Company: None Start At: None Ends At: None Location: None Description: None Title: IP legal adviser Company: None Start At: None Ends At: None Location: None Description: None Title: Legal Adviser Company: None Start At: None Ends At: None Location: None Description: None Title: Juriste marques Company: None Start At: None Ends At: None Location: None Description: None Title: Responsable section juridique - BPI Company: None Start At: None Ends At: None Location: None Description: None | W8: School: Paris-Pantheon-Assas University Degree: Doctor of Law (JD), Propriété intellectuelle Activities: None | Y8: Directrice Juridique / Legal Director chez Institut Imagine
A9: Jeff Graf | B9: Jeff Graf.png | C9: https://www.linkedin.com/in/jeff-graf-b557684 | D9: 1625 | E9: jeff.graf@sandboxaq.com | F9: Global Head of Business Development @ SandboxAQ | G9: SandboxAQ | H9: Software Development | I9: https://www.sandboxaq.com/ | J9: https://www.linkedin.com/company/sandboxaq/ | L9: 51-200 | M9: 1 yr 7 mos | N9: United States | O9: San Francisco, California | V9: Title: Global Head of Business Development @ SandboxAQ Company: None Start At: None Ends At: None Location: None Description: None Title: Co-Founder Company: None Start At: None Ends At: None Location: None Description: None Title: Independent Consultant Company: None Start At: None Ends At: None Location: None Description: None Title: Investor & Advisor Company: None Start At: None Ends At: None Location: None Description: None Title: Chief Commercial Officer (CCO) Company: None Start At: None Ends At: None Location: None Description: None Title: Chief Business Officer (CBO) Company: None Start At: None Ends At: None Location: None Description: None Title: Senior Director, Business Development Company: None Start At: None Ends At: None Location: None Description: None Title: Director, Business Development Company: None Start At: None Ends At: None Location: None Description: None Title: Sr Engagement Manager Company: None Start At: None Ends At: None Location: None Description: None Title: Engagement Manager Company: None Start At: None Ends At: None Location: None Description: None Title: Post doctoral fellow Company: None Start At: None Ends At: None Location: None Description: None | W9: School: EPFL Degree: Ph.D., Physics Activities: None School: University of California, Berkeley Degree: PhD, Physics Activities: None School: EPFL Degree: Master, Physics Activities: None | X9: People and thought leader with 15 years of experience across go-to-market strategy and business development in deep-tech. With a broad industry experience, a C-suite network, a business foundation, a multicultural background, and a science PhD, I am an engaging and energizing leader and doer who can motivate, coach, and influence others without formal power across boundaries and levels in large and small organizations. I have a track record of leading and closing complex 100m+ deals with value share across pharma, food and agriculture, and planetary health. | Y9: Biotech executive, ex-Mckinsey | Z9: Jeff_Graf.png
A10: Jack Hidary | B10: Jack Hidary.png | C10: https://www.linkedin.com/in/jackhidary | D10: 37202 | E10: jack@sandboxaq.com | F10: Chief Executive Officer | G10: SandboxAQ | H10: Software Development | I10: https://www.sandboxaq.com/ | J10: https://www.linkedin.com/company/sandboxaq/ | L10: 51-200 | M10: 4 yrs 3 mos | N10: United States | O10: Palo Alto, California | P10: Spanish | V10: Title: Chief Executive Officer Company: None Start At: None Ends At: None Location: None Description: None Title: Author Company: None Start At: None Ends At: None Location: None Description: None Title: Board Member Company: None Start At: None Ends At: None Location: None Description: None Title: Founder Company: None Start At: None Ends At: None Location: None Description: None Title: Sandbox Group Director Company: None Start At: None Ends At: None Location: None Description: None Title: Chairman Company: None Start At: None Ends At: None Location: None Description: None Title: Board member Company: None Start At: None Ends At: None Location: None Description: None Title: Member Company: None Start At: None Ends At: None Location: None Description: None Title: GLT - DAVOS Company: None Start At: None Ends At: None Location: None Description: None Title: Chairman and Co-founder Company: None Start At: None Ends At: None Location: None Description: None Title: Co-founder, Chairman and CEO Company: None Start At: None Ends At: None Location: None Description: None | W10: School: Columbia University Degree: Philosophy and Neuroscience Activities: None School: National Institutes of Health Degree: Stanley Fellowship in Clinical Neuroscience, Functional neuroimaging Activities: None | X10: Jack is the CEO of SandboxAQ, an enterprise SaaS company delivering AI and quantum tech (AQ) solutions for large enterprises in banking, biopharma, government, and other sectors. Jack is the author of Quantum Computing: An Applied Approach (Springer, 2nd edition), one of the leading textbooks in the field. Combining both quantum computing theory with hands-on coding, the book is extensively used in university classrooms and corporate up-skilling programs. Jack also co-authored the paper Transitioning Organizations to Post-Quantum Cryptography, published in Nature. Jack has been recognized for his leadership by organizations such as HealthCorps and Young Presidents’ Organization (YPO), and he is a member of the World Economic Forum’s Global Future Council. He frequently speaks at major business and technical conferences hosted by The Economist, Forbes, World Economic Forum, Cog X, MIT, and more. As a serial entrepreneur, Jack has launched and led multiple tech startups, including EarthWeb/Dice, a leading tech marketplace, and Vista Research, a fintech company that he and his team sold to Standard and Poors/McGraw-Hill. Jack has served as a board member, advisor, or trustee for numerous organizations, including BT Global, the XPrize, the National Renewable Energy Lab (NREL), the Partnership for New York City, Trickle Up, and the Council on Foreign Relations. Jack studied neuroscience at Columbia and subsequently received the Stanley Fellowship in Clinical Neuroscience at the National Institutes of Health, where he worked on functional brain imaging and neural networks. Jack's Erdös Number is 3. | Y10: SandboxAQ- AI and Quantum | Z10: Jack_Hidary.png
A11: Mitchell Krane | B11: Mitchell Krane.png | C11: https://www.linkedin.com/in/mitchellkrane | D11: 534 | E11: mitchell.krane@sandboxaq.com | F11: Director, Solution Architects & Customer Success | G11: SandboxAQ | H11: Software Development | I11: https://www.sandboxaq.com/ | J11: https://www.linkedin.com/company/sandboxaq/ | L11: 51-200 | M11: 4 mos | N11: United States | O11: Seattle, Washington | U11: Name: AWS Certified Solutions Architect - Associate Authority: Amazon Web Services (AWS) Date: Unknown URL: https://linkedin.com/company/2382910 Name: Certified Information Systems Security Professional (CISSP) Authority: ISC2 Date: Unknown URL: https://linkedin.com/company/26753 | V11: Title: Director, Solution Architects & Customer Success Company: None Start At: None Ends At: None Location: None Description: None Title: Manager, Solutions Architects Company: None Start At: None Ends At: None Location: None Description: None Title: Senior Solutions Architect Company: None Start At: None Ends At: None Location: None Description: None Title: Sr Specialist Solutions Architect - Security Company: None Start At: None Ends At: None Location: None Description: None Title: Specialist Solutions Architect - Security Company: None Start At: None Ends At: None Location: None Description: None Title: Professional Services Consultant - Security Company: None Start At: None Ends At: None Location: None Description: None Title: Endpoint Security Engineer Company: None Start At: None Ends At: None Location: None Description: None Title: Endpoint Security Administrator Company: None Start At: None Ends At: None Location: None Description: None Title: Tactical Craft Engineer/Gunner Company: None Start At: None Ends At: None Location: None Description: None Title: Cyber Security Analyst Company: None Start At: None Ends At: None Location: None Description: None Title: Service Desk Supervisor Company: None Start At: None Ends At: None Location: None Description: None | W11: School: Arizona State University Degree: Bachelor of Science, Information Technology Activities: None | Y11: Director, Solution Architects & Customer Success | Z11: Mitchell_Krane.png
A12: Reese Brown | B12: Reese Brown.png | C12: https://www.linkedin.com/in/reese-brown-74262246 | D12: 4096 | E12: reese.brown@quantinuum.com | F12: Sr. Director Talent Management | G12: Quantinuum | H12: Computer and Network Security | I12: https://www.quantinuum.com | J12: https://www.linkedin.com/company/quantinuumqc/ | L12: 201-500 | M12: 4 mos | N12: United States | O12: Salt Lake City, Utah | V12: Title: Sr. Director Talent Management Company: None Start At: None Ends At: None Location: None Description: None Title: Director Talent Management Company: None Start At: None Ends At: None Location: None Description: None Title: Sr. Talent Manager Company: None Start At: None Ends At: None Location: None Description: None Title: Human Resources Manager Company: None Start At: None Ends At: None Location: None Description: None Title: Sr. HR Services Manager - Mergers & Acquisitions Company: None Start At: None Ends At: None Location: None Description: None Title: HR Manager- Honeywell Quantum Solutions Company: None Start At: None Ends At: None Location: None Description: None Title: HR Manager Company: None Start At: None Ends At: None Location: None Description: None Title: Sr. Staffing Specialist Company: None Start At: None Ends At: None Location: None Description: None Title: Sr. HR Generalist Company: None Start At: None Ends At: None Location: None Description: None Title: HR Generalist Company: None Start At: None Ends At: None Location: None Description: None Title: Human Resources Intern Company: None Start At: None Ends At: None Location: None Description: None Title: Human Resources Intern Company: None Start At: None Ends At: None Location: None Description: None Title: Business Intern Company: None Start At: None Ends At: None Location: None Description: None Title: Agency Marketing Member Company: None Start At: None Ends At: None Location: None Description: None | W12: School: Utah State University Degree: Master of Business Administration - MBA Activities: None School: Utah State University Degree: Master's degree, Human Resources Management/Personnel Administration, General Activities: None School: Utah State University Degree: Bachelor's degree, Marketing Activities: None | Y12: Sr. Director Talent Management at Quantinuum | Z12: Reese_Brown.png
A13: Kirsty E. | C13: https://www.linkedin.com/in/kirstyewing | D13: 819 | E13: kirsty.e@sandboxaq.com | F13: Director of User Experience, AI Generation Engine | G13: SandboxAQ | H13: Software Development | I13: https://www.sandboxaq.com/ | J13: https://www.linkedin.com/company/sandboxaq/ | L13: 51-200 | M13: 7 mos | N13: United States | O13: San Francisco Bay Area | Q13: Title: How to build the virtual cell with artificial intelligence: Priorities and opportunities Source: Cell Summary: Cells are essential to understanding health and disease, yet traditional models fall short of modeling and simulating their function and behavior. Advances in AI and omics offer groundbreaking opportunities to create an AI virtual cell (AIVC), a multi-scale, multi-modal large-neural-network-based model that can represent and simulate the behavior of molecules, cells, and tissues across diverse states. This Perspective provides a vision on their design and how collaborative efforts to build AIVCs will transform biological research by allowing high-fidelity simulations, accelerating discoveries, and guiding experimental studies, offering new opportunities for understanding cellular functions and fostering interdisciplinary collaborations in open science. URL: https://www.cell.com/cell/fulltext/S0092-8674(24)01332-1 Title: Scientific Open Source Software Archetypes Source: Unknown Summary: This information resource was developed by the Open Source Working Group at Chan Zuckerberg Initiative. It presents a framework and guidelines for the many ways of doing OSS in science, and is based on the Mozilla OSS Archetypes. We set out to create a set of resources to help project developers and teams: Understand different models of open source projects Identify which of these models is most appropriate for achieving their project’s goals Prioritize the most important open source best practices with tailored recommendations based on their archetype. URL: https://github.com/chanzuckerberg/oss-archetypes Title: Simultaneous detection of pathogens and antimicrobial resistance genes with the open source, cloud-based, CZ ID pipeline Source: Unknown Summary: Antimicrobial resistant (AMR) pathogens represent urgent threats to human health, and their surveillance is of paramount importance. Metagenomic next generation sequencing (mNGS) has revolutionized such efforts, but remains challenging due to the lack of open-access bioinformatics tools capable of simultaneously analyzing both microbial and AMR gene sequences. To address this need, we developed the Chan Zuckerberg ID (CZ ID) AMR module, an open-access, cloud-based workflow designed to integrate detection of both microbes and AMR genes in mNGS and whole-genome sequencing (WGS) data. URL: https://www.biorxiv.org/content/10.1101/2024.04.12.589250v2 | V13: Title: Director of User Experience, AI Generation Engine Company: None Start At: None Ends At: None Location: None Description: None Title: Director of Product Design and User Experience Research Company: None Start At: None Ends At: None Location: None Description: None Title: User Experience Research Manager Company: None Start At: None Ends At: None Location: None Description: None Title: Staff User Experience Researcher - Science Company: None Start At: None Ends At: None Location: None Description: None Title: Interim Design and UX Research Director Company: None Start At: None Ends At: None Location: None Description: None Title: Senior User Experience Researcher - Science Company: None Start At: None Ends At: None Location: None Description: None Title: Design Researcher Company: None Start At: None Ends At: None Location: None Description: None Title: Innovation Consultant Company: None Start At: None Ends At: None Location: None Description: None Title: Great Recovery Design Resident Company: None Start At: None Ends At: None Location: None Description: None Title: Senior Researcher Company: None Start At: None Ends At: None Location: None Description: None Title: Research Assistant - Prototyping Sustainable Structural Systems Company: None Start At: None Ends At: None Location: None Description: None | W13: School: Cranfield University Degree: Masters, Design for Innovation and Sustainability Activities: None School: Ithaca College Degree: BS, Integrated Marketing Communications Activities: None | Y13: Director of User Experience, AI Generation Engine
A14: Elvira Shishenina | B14: Elvira Shishenina.png | C14: https://www.linkedin.com/in/elvira-shishenina | D14: 12091 | E14: elvira.shishenina@quantinuum.com | F14: Senior Director - Strategic Initiatives | G14: Quantinuum | H14: Computer and Network Security | I14: https://www.quantinuum.com | J14: https://www.linkedin.com/company/quantinuumqc/ | L14: 201-500 | M14: 1 yr 7 mos | N14: United Arab Emirates | O14: United Arab Emirates | P14: English, French | V14: Title: Senior Director - Strategic Initiatives Company: None Start At: None Ends At: None Location: None Description: None Title: Scientific Advisor Company: None Start At: None Ends At: None Location: None Description: None Title: Business Advisor Company: None Start At: None Ends At: None Location: None Description: None Title: Co-founder Company: None Start At: None Ends At: None Location: None Description: None Title: President and Co-founder Company: None Start At: None Ends At: None Location: None Description: None Title: President Company: None Start At: None Ends At: None Location: None Description: None Title: Quantum Computing Team Lead Company: None Start At: None Ends At: None Location: None Description: None Title: Quantum Computing Scientist Company: None Start At: None Ends At: None Location: None Description: None Title: Doctoral Student Company: None Start At: None Ends At: None Location: None Description: None | W14: School: École Polytechnique Degree: Ingénieur Polytechnicien (X2011); Master of Science - MS, Computational & Applied Mathematics Activities: None School: University of Pau and Adour Countries Degree: Doctor of Philosophy - PhD, Mathematics Activities: None School: Novosibirsk State University (NSU) Degree: Bachelor of Science - BS, Mathematics; Master of Science - MS, Mechanics & Mathematical Modeling Activities: None | Y14: Strategic Initiatives at Quantinuum | Z14: Elvira_Shishenina.png
A15: Andrea W. | B15: Andrea W.png | C15: https://www.linkedin.com/in/awilliston | D15: 823 | F15: Senior Director, Tax and Treasury | G15: Quantinuum | H15: Computer and Network Security | I15: https://www.quantinuum.com | J15: https://www.linkedin.com/company/quantinuumqc/ | L15: 201-500 | M15: 3 mos | N15: United States | O15: Los Angeles, California | U15: Name: CPA - California Authority: Date: Unknown URL: None | V15: Title: Senior Director, Tax and Treasury Company: None Start At: None Ends At: None Location: None Description: None Title: Head of Tax and Treasury Company: None Start At: None Ends At: None Location: None Description: None Title: Director of Tax Accounting Company: None Start At: None Ends At: None Location: None Description: None Title: Head of Global Income Tax Provision and Compliance Company: None Start At: None Ends At: None Location: None Description: None Title: Senior Manager, Tax Reporting Company: None Start At: None Ends At: None Location: None Description: None Title: Tax Senior Manager Company: None Start At: None Ends At: None Location: None Description: None Title: Director of Tax Accounting Company: None Start At: None Ends At: None Location: None Description: None Title: Tax Manager Company: None Start At: None Ends At: None Location: None Description: None Title: Tax Staff - Tax Manager Company: None Start At: None Ends At: None Location: None Description: None | W15: School: USC Marshall School of Business Degree: Master's degree, Business Taxation Activities: None School: University of Southern California Degree: Bachelor of Science - BS, Accounting Activities: None | X15: Specialties: Corporate taxation, FAS 109, FIN 48, Sox 404 | Y15: Tax and Treasury at Quantinuum | Z15: Andrea_W..png
A16: Stanton Fischer | B16: Stanton Fischer.png | C16: https://www.linkedin.com/in/stanton-fischer-mas-cpp-ccep-ccep-i-284916159 | D16: 420 | F16: Director of Risk & Compliance | G16: Quantinuum | H16: Computer and Network Security | I16: https://www.quantinuum.com | J16: https://www.linkedin.com/company/quantinuumqc/ | L16: 201-500 | M16: 1 yr 6 mos | N16: United States | O16: Denver Metropolitan Area | T16: Title: Excecutive Director Start At: 06/2019 Ends At: Present Company: עמותת לוחמים לחיים / Fighters for Life Cause: Health Description: Founding member of the U.S.-based branch focusing on PTSD identification and treatment for law enforcement officers and soldiers. A core goal is to create an exchange program between officers and soldiers from the U.S. and Israel in order to share experiences, best practices, and establish permanent treatment facilities in both countries. Our goal is to bring the same level of awareness of PTSD in law enforcement as there is for military veterans. | U16: Name: CCEP-I Authority: Certified Compliance & Ethics Professional-International (CCEP-I)® Date: Unknown URL: https://linkedin.com/company/18861316 Name: ASIS Member Authority: ASIS International Date: 2022-1 URL: https://linkedin.com/company/30614 | V16: Title: Director of Risk & Compliance Company: None Start At: None Ends At: None Location: None Description: None Title: Director Of Global Security Company: None Start At: None Ends At: None Location: None Description: None Title: Security Operations Manager Company: None Start At: None Ends At: None Location: None Description: None Title: Security Consultant Company: None Start At: None Ends At: None Location: None Description: None Title: Director of Corporate Security and Government Liaison Company: None Start At: None Ends At: None Location: None Description: None Title: Managing Director Company: None Start At: None Ends At: None Location: None Description: None Title: Supervisory Special Agent Company: None Start At: None Ends At: None Location: None Description: None Title: Police Officer Company: None Start At: None Ends At: None Location: None Description: None Title: Major Company: None Start At: None Ends At: None Location: None Description: None | W16: School: University of Denver Degree: Master of Science - MS, Security Management Activities: None School: University of Colorado Boulder Degree: Bachelor of Arts - BA, Political Science Activities: None | X16: Security and compliance leader with over 25 years experience in varied intelligence, counterintelligence, and criminal investigations domestically and abroad. Led several projects developing and implementing security solutions to identify external and internal threats, mitigating threats, and ensuring continuity of operations. Current Top Secret SCI security clearance with polygraph. | Y16: Director of Risk and Compliance | Quantinuum | Positively Changing the World Through the Application of Quantum Computing | Z16: Stanton_Fischer,_MAS,_CPP,_CCEP,_CCEP-I.png
A17: Steve Brocklebank MBA | B17: Steve Brocklebank MBA.png | C17: https://www.linkedin.com/in/steve-brocklebank-mba-7935481a | D17: 7387 | E17: steve.brocklebank@cambridgequantum.com | F17: HR Director | G17: Quantinuum | H17: Computer and Network Security | I17: https://www.quantinuum.com | J17: https://www.linkedin.com/company/quantinuumqc/ | L17: 201-500 | M17: 7 yrs 2 mos | N17: United Kingdom | O17: Leicester, England | V17: Title: HR Director Company: None Start At: None Ends At: None Location: None Description: None Title: Group Human Resources Director Company: None Start At: None Ends At: None Location: None Description: None Title: Group HR Manager (Head of HR) Company: None Start At: None Ends At: None Location: None Description: None Title: HR Manager Company: None Start At: None Ends At: None Location: None Description: None Title: HR Coordinator Company: None Start At: None Ends At: None Location: None Description: None Title: HR Administrator Company: None Start At: None Ends At: None Location: None Description: None | W17: School: University of Leicester Degree: MBA, Master of Business Administration Activities: None School: The University of Huddersfield Degree: MCIPD Activities: None School: The University of Huddersfield Degree: BA (Hons), Business Studies Activities: None School: Ashridge Business School Degree: None Activities: None | Y17: HR Director at Quantinuum | Z17: Steve_Brocklebank_MBA.png
A18: Guillaume Schmid | B18: Guillaume Schmid.png | C18: https://www.linkedin.com/in/guillaume-schmid-4b145a3 | D18: 495 | E18: guillaume.schmid@pasqal.com | F18: Software Team Lead | G18: Pasqal | H18: IT Services and IT Consulting | I18: https://www.pasqal.com/ | J18: https://www.linkedin.com/company/pasqal/ | L18: 201-500 | M18: 1 yr 6 mos | N18: France | O18: Lognes, Île-de-France | P18: English, French | Q18: Title: Label-free imaging of large samples: 3D rendering and morphological analysis within histological workflows using serial block face imaging Source: BioRxiv Summary: Serial block face imaging (SFBI) is a method used to generate 3-dimensional (3D) reconstruction of a sample via serial image acquisition. Several SBFI approaches have been proposed for large samples, differing in the ability to generate contrast as well as in the nature of the detected signal. We propose a new system that detects the endogenous autofluorescence signal of paraffin-embedded samples. The sample preparation is simplified compared to other approaches, and adapted to be integrated into a routine histological preparation. More specifically, it was designed to limit reagent toxicity and to be compatible with downstream histological processing. We show the usefulness of the technique with a wide range of tissues based on the intrinsic autofluorescence signal. Optimization of quality section recovery offers the possibility to develop correlative approaches and multimodal analysis between the 3D dataset with the 2-dimensional sections. In addition, contrast and resolution of block-face images allow us to successfully perform post processing analysis and morphology quantifications. Overall, our methodology offers a simple, cost effective and rapid approach to obtain quantitative data on a large sample with no specific staining. URL: https://www.biorxiv.org/content/10.1101/2022.05.03.488912v1 Title: Multicolor probe-based confocal laser endomicroscopy: a new world for in vivo and real-time cellular imaging Source: Unknown Summary: None URL: None | U18: Name: An Intuitive Introduction to Probability Authority: Coursera Course Certificates Date: 2017-4 URL: None Name: Neural Networks for Machine Learning Authority: Coursera Course Certificates Date: 2017-2 URL: None | V18: Title: Software Team Lead Company: None Start At: None Ends At: None Location: None Description: None Title: Co founder, Software R&D Director and Lead Developper. Company: None Start At: None Ends At: None Location: None Description: None Title: Software Research and Development Director & Lead Developper. Company: None Start At: None Ends At: None Location: None Description: None Title: Freelance Developper Company: None Start At: None Ends At: None Location: None Description: None Title: Lead Developper / R&D Manager Company: None Start At: None Ends At: None Location: None Description: None Title: Developper Company: None Start At: None Ends At: None Location: None Description: None | W18: School: ESIEA - École d'Ingénieur·e·s d'un numérique utile Degree: French bac+5 Ingenieur diploma (Masters equivalent), Image synthesis, artificial intelligence, software architecture. Activities: None School: ESIEA Degree: Master of Science., Computer Software Engineering Activities: None | X18: I have a very good experience working with a research team. Between a great idea or algorithm and a product, there is a huge gap. A different set of complementary skills are needed to cross it. My strength is to build and lead those kinds of teams of Ph.D. and Software developers and design some frameworks and tools for the researchers to explore their ideas faster and implement robust customer products. As a team manager, I drive innovation and push the team to learn and experiment. Building a team to work on big medical-grade software requires good processes, as well as communicative dedication and motivation. And as a CTO of Kaer Labs, I provide a long-term vision for our software products and technologies. Main responsabilities in current position at Pasqal - Software team management - Software architecture. - interface with many other teams (hardware, industrialization and other software teams). Main responsibilities in the previous position: Manage software teams. Design the architecture of our software products (Rust, C++, Python) and train the team on this framework. Build also Tech demos and prototypes. Provide a technological vision and roadmap for the company. Work with a remote team. Recruiting and Building remote teams (I recruited a small team in Vietnam). Specialties: - Team management and mentoring/training. - Software architecture, internal design, and development. - Software development process (medical grade). - Strong software and architecture design skills. - Good technical and personal communication. From a personal standpoint, I have a real passion for Machine learning, software architecture, and technology in general. | Y18: Software Team Lead & Architect at Pasqal - Quantum Operating System | Z18: Guillaume_Schmid.png
A19: Jean-Yves Quentel | C19: https://www.linkedin.com/in/jquentel | D19: 3208 | F19: Group CFO | G19: Pasqal | H19: IT Services and IT Consulting | I19: https://www.pasqal.com/ | J19: https://www.linkedin.com/company/pasqal/ | L19: 201-500 | M19: 6 mos | N19: France | O19: Paris, Île-de-France | V19: Title: Group CFO Company: None Start At: None Ends At: None Location: None Description: None Title: Founder Company: None Start At: None Ends At: None Location: None Description: None Title: Group CFO & IR Company: None Start At: None Ends At: None Location: None Description: None Title: Chief Financial Officer Company: None Start At: None Ends At: None Location: None Description: None Title: Group CFO Company: None Start At: None Ends At: None Location: None Description: None Title: Group CFO Company: None Start At: None Ends At: None Location: None Description: None Title: Co-founder and CEO Company: None Start At: None Ends At: None Location: None Description: None Title: CFO Company: None Start At: None Ends At: None Location: None Description: None Title: Managing Director Company: None Start At: None Ends At: None Location: None Description: None Title: Director Company: None Start At: None Ends At: None Location: None Description: None Title: Co-founder & CEO Company: None Start At: None Ends At: None Location: None Description: None Title: Partner Company: None Start At: None Ends At: None Location: None Description: None Title: Director Company: None Start At: None Ends At: None Location: None Description: None Title: Senior Vice-President Company: None Start At: None Ends At: None Location: None Description: None Title: Investment Manager Company: None Start At: None Ends At: None Location: None Description: None Title: Analyst Company: None Start At: None Ends At: None Location: None Description: None | W19: School: ESSEC Business School Degree: None Activities: None School: ESSEC Business School Degree: None Activities: None | Y19: Group CFO in Tech Scale-ups
A20: Jean-Marc KERISIT | B20: Jean-Marc KERISIT.png | C20: https://www.linkedin.com/in/jkerisit | D20: 2321 | F20: VP Engineering Center & Hardware Platform | G20: Pasqal | H20: IT Services and IT Consulting | I20: https://www.pasqal.com/ | J20: https://www.linkedin.com/company/pasqal/ | L20: 201-500 | M20: 1 yr 3 mos | N20: France | O20: St.-Maur-des-Fossés, Île-de-France | P20: English, French | S20: Title: METHOD AND SYSTEM FOR AUTOMATICALLY CHECKING THE AUTHENTICITY OF AN IDENTITY DOCUMENT Issuer: US 20120324534 Issued On: Dec 20, 2012 Description: None Title: Data analysis to optimize an explicative rule for analyzing the operation of a production line Issuer: US 7664722 Issued On: Feb 16, 2010 Description: None Title: Process for the iterative construction of an explanatory model Issuer: US 7617171 Issued On: Nov 10, 2009 Description: None Title: Editing process for an explanatory model Issuer: US 7509297 Issued On: Mar 24, 2009 Description: None | T20: Title: Vice-président Start At: 09/2011 Ends At: 09/2013 Company: Les Amateurs! Cause: Arts_and_culture Description: Organization of a music festival in France (Théâtre du Châtelet) and worldwide (Shanghai, Budapest, St-Petersburg, Buenos-Aires, Rosario) Title: Président Start At: 2014 Ends At: Present Company: Musicami Cause: Arts_and_culture Description: Organization of chamber music concerts Title: Concerts in retirement homes, hospitals and prisons Start At: 01/2007 Ends At: Present Company: Association Volontariat et Soutien par l'Art (VSArt) Cause: Arts_and_culture Description: None | V20: Title: VP Engineering Center & Hardware Platform Company: None Start At: None Ends At: None Location: None Description: None Title: VP Competency Centers Company: None Start At: None Ends At: None Location: None Description: None Title: Founder and Managing Director Company: None Start At: None Ends At: None Location: None Description: None Title: Directeur Practice CTO# Company: None Start At: None Ends At: None Location: None Description: None Title: Interim Chief Product and Technology Officer Company: None Start At: None Ends At: None Location: None Description: None Title: CTO Company: None Start At: None Ends At: None Location: None Description: None Title: Transition CTO Company: None Start At: None Ends At: None Location: None Description: None Title: Vice-President Products Company: None Start At: None Ends At: None Location: None Description: None Title: Transition VP Products Company: None Start At: None Ends At: None Location: None Description: None Title: Transition COO Company: None Start At: None Ends At: None Location: None Description: None Title: VP R&D (transition) Company: None Start At: None Ends At: None Location: None Description: None Title: Senior Vice President Technology at ADVESTIGO Company: None Start At: None Ends At: None Location: None Description: None Title: Member of the Scientific Committee Company: None Start At: None Ends At: None Location: None Description: None Title: CTO - VP R&D Company: None Start At: None Ends At: None Location: None Description: None Title: Founder & CEO Company: None Start At: None Ends At: None Location: None Description: None Title: Director of R&D, Chief Architect Company: None Start At: None Ends At: None Location: None Description: None Title: Director of the ITPL Software Activity Company: None Start At: None Ends At: None Location: None Description: None Title: Technical Manager for Artificial Intelligence Products & Applications Company: None Start At: None Ends At: None Location: None Description: None Title: Searcher in Artificial Intelligence Company: None Start At: None Ends At: None Location: None Description: None | W20: School: École Polytechnique Degree: Engineer Activities: None School: Université Paris VII Degree: PhD, Theoretical Computer Sciences Activities: None School: Ecole Nationale de la Statistique et de l'Administration Economique Degree: None Activities: None School: Lycée Châteaubriand Degree: Baccalauréat Abitur Activities: None School: Lycée Chateaubriand Degree: Classes préparatoires Activities: None | X20: Specialties: Management, Organization, Technological Strategy,Patents, R&D, Quality | Y20: Deep experience in Tech. Various CPTO and CTO Positions | Z20: Jean-Marc_KERISIT.png
A21: Far McKon | B21: Far McKon.png | C21: https://www.linkedin.com/in/far-mckon | D21: 693 | E21: far.mckon@ionq.com | F21: Director of Application Engineering | G21: IonQ | H21: Computers and Electronics Manufacturing | I21: https://ionq.com/ | J21: https://www.linkedin.com/company/ionq-co/ | L21: 201-500 | M21: 3 mos | N21: United States | O21: Media, Pennsylvania | P21: English, German | V21: Title: Director of Application Engineering Company: None Start At: None Ends At: None Location: None Description: None Title: CTO Company: None Start At: None Ends At: None Location: None Description: None Title: Head of Software Company: None Start At: None Ends At: None Location: None Description: None Title: Chief Innovator Company: None Start At: None Ends At: None Location: None Description: None Title: (Interim) Nerd Herder (Lead Software Developer) Company: None Start At: None Ends At: None Location: None Description: None Title: Embedded Linux Nerd Company: None Start At: None Ends At: None Location: None Description: None Title: Embedded Linux Consultant Company: None Start At: None Ends At: None Location: None Description: None Title: President (aka Instigator) Company: None Start At: None Ends At: None Location: None Description: None Title: Lead Programmer & Co-Founder Company: None Start At: None Ends At: None Location: None Description: None Title: Scanning, Processing, Imaging Developer Company: None Start At: None Ends At: None Location: None Description: None Title: Embedded Software Developer Company: None Start At: None Ends At: None Location: None Description: None Title: Software Developer Company: None Start At: None Ends At: None Location: None Description: None | W21: School: Binghamton University Degree: M.S., Computer Science Activities: None School: School of Hard Knocks Degree: BS of BS, BS Activities: None School: Gymnasium Ulricianum Degree: High School, Exchange Student Activities: None | X21: I work where the Venn Diagram of Hardware, Software, and community meet. I'm particularly interested in peer collaboration, and Open Source projects as accelerant for growth. Nerd Herder. Panic Manager. I started from the bottom; Linux drivers, firmware, embedded programming. Now I'm here; CTO, Department Development, and (re)building Engineering teams. From NeatDesk through MakerWare, the products I have worked on have ended up in magazines, TV shows, and stores around the world. Even a few in museums. They run on thousands of laptops and in workshops every day, competently and quietly doing their job of making life easier. Specialties: Project Management, Nerd Herding, Panic Management, Start-ups. Leading teams of domain experts, and empowering them to do amazing things. | Y21: Builds the teams that builds beloved products. Inhales problems, exhales solutions. | Z21: Far_McKon.png
A22: Nikhil Dhingra | B22: Nikhil Dhingra.png | C22: https://www.linkedin.com/in/ndhingra | D22: 4213 | E22: nikhil.dhingra@ionq.com | F22: Senior Director of Product Marketing | G22: IonQ | H22: Computers and Electronics Manufacturing | I22: https://ionq.com/ | J22: https://www.linkedin.com/company/ionq-co/ | L22: 201-500 | M22: 2 yrs 10 mos | N22: United States | O22: Los Angeles Metropolitan Area | Q22: Title: The default pull: An experimental demonstration of subtle default effects on preferences Source: Journal of Judgment & Decision Making Summary: Over 25 citations in major journals and publications URL: http://journal.sjdm.org/10/10831a/jdm10831a.html | U22: Name: Become a Manager Authority: LinkedIn Date: 2018-12 URL: https://linkedin.com/company/1337 Name: Rewarding Employees Authority: LinkedIn Date: 2018-12 URL: https://linkedin.com/company/1337 | V22: Title: Senior Director of Product Marketing Company: None Start At: None Ends At: None Location: None Description: None Title: Director of Product Marketing Company: None Start At: None Ends At: None Location: None Description: None Title: Ambassador, Contributor, Speaker Company: None Start At: None Ends At: None Location: None Description: None Title: Director of Product Marketing Company: None Start At: None Ends At: None Location: None Description: None Title: Director of Product Marketing Company: None Start At: None Ends At: None Location: None Description: None Title: Cofounder, Advisor Company: None Start At: None Ends At: None Location: None Description: None Title: Product Marketing Company: None Start At: None Ends At: None Location: None Description: None Title: Head of Product Marketing Company: None Start At: None Ends At: None Location: None Description: None Title: Product Marketing Company: None Start At: None Ends At: None Location: None Description: None Title: Product Marketing Company: None Start At: None Ends At: None Location: None Description: None Title: Product Manager, Platform Safety and Security Company: None Start At: None Ends At: None Location: None Description: None | W22: School: University of Pennsylvania Degree: BA, Philosophy, Politics, and Economics (PPE) Activities: None School: Jesuit Dallas Degree: High School Diploma Activities: None | X22: Top 100 Product Marketing Influencer | Strategic Storyteller | B2B SaaS GTM Leader Product marketing is the engine that makes great ideas real — and revenue-generating. I specialize in bringing clarity to complexity, speed to execution, and resonance to messaging. Whether it’s launching breakthrough products, crafting differentiated positioning, or enabling sales to close bigger, faster, smarter — I make things happen. With 15+ years of product marketing and go-to-market experience across startups and global tech brands (Salesforce, Apigee/Google Cloud, ServiceTitan, IonQ), I’ve led high-impact initiatives in: 🔹 Quantum Computing & AI 🔹 B2B SaaS, Vertical SaaS, & RevOps 🔹 Sales Engagement & Enablement 🔹 APIs, Big Data, IoT 🔹 Commercial/Residential Services Tech What I do best: — Build clear, differentiated messaging that resonates with real buyers — Drive launches that land and scale — Empower go-to-market teams with tools that work — Turn complex products into simple, compelling stories Creative, fast-moving, and execution-focused. I thrive in ambiguity and lead with clarity. All views my own. | Y22: Product Marketing Leader | Quantum Computing & Deep Tech | Go-to-Market, Positioning & Storytelling | IonQ | ex–D-Wave, ServiceTitan, Salesforce | Z22: Nikhil_Dhingra.png
A23: Diego Heinrich | B23: Diego Heinrich.png | C23: https://www.linkedin.com/in/diego-heinrich-1295a8ba | D23: 1079 | E23: diego.heinrich@ionq.com | F23: Senior Director - Strategic Partnerships | G23: IonQ | H23: Computers and Electronics Manufacturing | I23: https://ionq.com/ | J23: https://www.linkedin.com/company/ionq-co/ | L23: 201-500 | M23: 1 yr 3 mos | N23: United Arab Emirates | O23: United Arab Emirates | P23: English, German | V23: Title: Senior Director - Strategic Partnerships Company: None Start At: None Ends At: None Location: None Description: None Title: Project Leader Company: None Start At: None Ends At: None Location: None Description: None Title: Manager Company: None Start At: None Ends At: None Location: None Description: None Title: Consultant Company: None Start At: None Ends At: None Location: None Description: None Title: Business Analyst Company: None Start At: None Ends At: None Location: None Description: None Title: Investment Banking Summer Analyst Company: None Start At: None Ends At: None Location: None Description: None Title: Corporate Finance Intern Company: None Start At: None Ends At: None Location: None Description: None Title: M&A Intern Company: None Start At: None Ends At: None Location: None Description: None | W23: School: The London School of Economics and Political Science (LSE) Degree: Master’s Degree, Business Administration and Management, General Activities: None School: CEMS - The Global Alliance in Management Education Degree: Master’s Degree, Business Administration and Management, General Activities: None School: Esade Degree: Master’s Degree, Business Administration and Management, General Activities: None School: University of Cologne Degree: Bachelor’s Degree, Business Administration and Management, General Activities: None | Y23: Senior Director at IonQ | Z23: Diego_Heinrich.png
A24: Amy Smidutz | B24: Amy Smidutz.png | C24: https://www.linkedin.com/in/amy-smidutz-a0310526 | D24: 2140 | E24: amy.smidutz@ionq.com | F24: Senior Director of Resilience Engineering and Operations | G24: IonQ | H24: Computers and Electronics Manufacturing | I24: https://ionq.com/ | J24: https://www.linkedin.com/company/ionq-co/ | L24: 201-500 | M24: 2 yrs 5 mos | N24: United States | O24: Seattle, Washington | T24: Title: Interview Training Start At: None Ends At: Present Company: Year Up United Cause: Description: None Title: Training Camp + Draft Day Start At: None Ends At: Present Company: WTIA Cause: Description: None | V24: Title: Senior Director of Resilience Engineering and Operations Company: None Start At: None Ends At: None Location: None Description: None Title: Director, Delivery Engineering Company: None Start At: None Ends At: None Location: None Description: None Title: Engineering Manager, Resilience Engineering Company: None Start At: None Ends At: None Location: None Description: None Title: Director Of Engineering - Infrastructure Services & Data Company: None Start At: None Ends At: None Location: None Description: None Title: Engineering Manager Company: None Start At: None Ends At: None Location: None Description: None Title: Technical Program Manager Company: None Start At: None Ends At: None Location: None Description: None Title: Technical Program Manager Company: None Start At: None Ends At: None Location: None Description: None Title: Automation Engineer Company: None Start At: None Ends At: None Location: None Description: None Title: Performance Platform Engineer Company: None Start At: None Ends At: None Location: None Description: None Title: Windows / Linux Automation Engineer Company: None Start At: None Ends At: None Location: None Description: None Title: Lead Windows Hosting Administrator Company: None Start At: None Ends At: None Location: None Description: None Title: Windows Hosting Administrator Company: None Start At: None Ends At: None Location: None Description: None | X24: Senior technology leader who is passionate about building cohesive engineering teams that create exceptional software. I am experienced in Continuous Delivery and Resiliency at scale. I love building great environments for teams to do amazing work while having fun. I focus on growth for both ICs and leaders and am extremely excited by the amazing projects and opportunities that come from leading talented teams in a complex and ever-changing environment. | Y24: Resilience Engineering at IonQ | Z24: Amy_Smidutz.png
A25: Alexander Hill | B25: Alexander Hill.png | C25: https://www.linkedin.com/in/axdhill | D25: 593 | F25: Director, Quantum Engineering | G25: Rigetti Computing | H25: IT Services and IT Consulting | I25: http://rigetti.com | J25: https://www.linkedin.com/company/rigetti-computing/ | L25: 51-200 | M25: 2 yrs 3 mos | N25: United States | O25: San Francisco Bay Area | P25: English, Russian | V25: Title: Director, Quantum Engineering Company: None Start At: None Ends At: None Location: None Description: None Title: Senior Manager, Quantum Engineering Company: None Start At: None Ends At: None Location: None Description: None Title: Senior Quantum Systems Engineer Company: None Start At: None Ends At: None Location: None Description: None Title: Postdoctoral Researcher Company: None Start At: None Ends At: None Location: None Description: None Title: Graduate Research Assistant Company: None Start At: None Ends At: None Location: None Description: None Title: NDSEG Fellow Company: None Start At: None Ends At: None Location: None Description: None Title: Fulbright Fellow Company: None Start At: None Ends At: None Location: None Description: None | W25: School: University of Illinois Urbana-Champaign Degree: Doctor of Philosophy (Ph.D.), Physics Activities: None School: The University of North Carolina at Chapel Hill Degree: Bachelor's Degree, Physics, Mathematics Activities: None | Y25: Director, Quantum Engineering at Rigetti Computing | Z25: Alexander_Hill.png
A26: Jaume Casademont Planagumà | B26: Jaume Casademont Planagumà.png | C26: https://www.linkedin.com/in/jaume-casademont-planagumà-19493729 | D26: 497 | F26: Director financiero | G26: QUERA | H26: Retail Luxury Goods and Jewelry | I26: https://www.quera.es | J26: https://www.linkedin.com/company/quera1887/ | L26: 51-200 | M26: 8 yrs 7 mos | N26: Spain | O26: Girona, Catalonia | V26: Title: Director financiero Company: None Start At: None Ends At: None Location: None Description: None Title: Jefe Administracion Company: None Start At: None Ends At: None Location: None Description: None Title: Adjunto Gerencia Company: None Start At: None Ends At: None Location: None Description: None Title: Depto. Contable y Fiscal Company: None Start At: None Ends At: None Location: None Description: None | W26: School: Universitat de Girona Degree: Ciències Empresarials Activities: None School: grupo IOE Degree: MBA Administración y Dirección de Empresas Activities: None | Y26: Director Financiero en QUERA | Z26: Jaume_Casademont_Planagumà.png
A27: Kalan Snyder | B27: Kalan Snyder.png | C27: https://www.linkedin.com/in/kalan-snyder | D27: 829 | E27: ksnyder@rigetti.com | F27: Director of Software Engineering | G27: Rigetti Computing | H27: IT Services and IT Consulting | I27: http://rigetti.com | J27: https://www.linkedin.com/company/rigetti-computing/ | L27: 51-200 | M27: 6 yrs | N27: United States | O27: Seattle, Washington | P27: Arabic, German | U27: Name: Student Pilot Certificate Authority: Federal Aviation Administration Date: 2017-5 URL: https://linkedin.com/company/5039 Name: AWS Certified DevOps Engineer - Professional Authority: Amazon Web Services (AWS) Date: 2019-9 URL: https://linkedin.com/company/2382910 | V27: Title: Director of Software Engineering Company: None Start At: None Ends At: None Location: None Description: None Title: Full Stack Software Engineer Company: None Start At: None Ends At: None Location: None Description: None Title: Steering Committee Member Company: None Start At: None Ends At: None Location: None Description: None Title: Systems Development Engineer I-II Company: None Start At: None Ends At: None Location: None Description: None Title: Security Analyst (Intern) Company: None Start At: None Ends At: None Location: None Description: None Title: Lead System Engineer Company: None Start At: None Ends At: None Location: None Description: None Title: Cyber Security Specialist Company: None Start At: None Ends At: None Location: None Description: None Title: Intelligence Analyst Company: None Start At: None Ends At: None Location: None Description: None Title: Project Manager Company: None Start At: None Ends At: None Location: None Description: None Title: Training Mission Lead Company: None Start At: None Ends At: None Location: None Description: None Title: Intelligence Team Lead, Construction Project Manager, and Artillery Officer Company: None Start At: None Ends At: None Location: None Description: None | W27: School: Georgia Institute of Technology Degree: Master of Science (M.S.), Computer Science Activities: None School: United States Military Academy at West Point Degree: Bachelor of Science (BS), Mathematics and Arabic Language Activities: None School: Michigan State University Degree: None Activities: None | X27: Architect with a passion for bringing the power of the cloud to the everyday user. Proficient in rapid systems design and full-stack prototyping. | Y27: Quantum → Cloud @ Rigetti Computing | Z27: Kalan_Snyder.png
A28: Elliot Dower | C28: https://www.linkedin.com/in/elliotdower | D28: 6942 | E28: elliot.dower@ionq.com | F28: Director of International Talent Acquisition | G28: IonQ | H28: Computers and Electronics Manufacturing | I28: https://ionq.com/ | J28: https://www.linkedin.com/company/ionq-co/ | L28: 201-500 | M28: 1 mo | N28: United Kingdom | O28: Oxford, England | T28: Title: Infantry Start At: 07/2021 Ends At: Present Company: British Army Cause: Description: 1 (UK) Div, 19 Bde, 6 RIFLES, A Coy | V28: Title: Director of International Talent Acquisition Company: None Start At: None Ends At: None Location: None Description: None Title: Head of Talent Acquisition Company: None Start At: None Ends At: None Location: None Description: None Title: Lead Talent Partner Company: None Start At: None Ends At: None Location: None Description: None Title: Talent Acquisition Partner Company: None Start At: None Ends At: None Location: None Description: None Title: Senior Talent Partner Company: None Start At: None Ends At: None Location: None Description: None Title: Senior Consultant Company: None Start At: None Ends At: None Location: None Description: None Title: Consultant Company: None Start At: None Ends At: None Location: None Description: None | W28: School: University of Cambridge Degree: Business Administration and Management, General Activities: None School: Saïd Business School, University of Oxford Degree: Executive Education, MBA Fundamentals Activities: None | X28: Talent acquisition leader with over a decade of experience building high talent density teams across deep and frontier technology. I work at the intersection of hiring strategy and execution, helping companies secure world class talent and scale through complexity. | Y28: Director of International Talent Acquisition at IonQ
A29: Stefano Poletto | B29: Stefano Poletto.png | C29: https://www.linkedin.com/in/stefano-poletto-392a6966 | D29: 1121 | E29: stefano@rigetti.com | F29: Director, Quantum Engineering | G29: Rigetti Computing | H29: IT Services and IT Consulting | I29: http://rigetti.com | J29: https://www.linkedin.com/company/rigetti-computing/ | L29: 51-200 | M29: 4 yrs 2 mos | N29: United States | O29: United States | P29: English, German | Q29: Title: Modular Superconducting Qubit Architecture with a Multi-chip Tunable Coupler Source: Phys. Rev. Applied 21, 054063 Summary: We use a floating tunable coupler to mediate interactions between qubits on separate chips to build a modular architecture. We demonstrate three different designs of multichip tunable couplers using vacuum-gap capacitors or superconducting indium-bump bonds to connect the coupler to a microwave line on a common substrate and then connect to the qubit on the next chip. We show that the zero-coupling condition between qubits on separate chips can be achieved in each design and that the relaxation rates for the coupler and qubits are not noticeably affected by the extra circuit elements. Finally, we demonstrate two-qubit gate operations with fidelity at the same level as qubits with a tunable coupler on a single chip. Using one or more indium bonds does not degrade qubit coherence or impact the performance of two-qubit gates. URL: https://journals.aps.org/prapplied/abstract/10.1103/PhysRevApplied.21.054063 Title: Full control of superconducting qubits with combined on-chip microwave and flux lines Source: Appl. Phys. Lett. 119, 144001 Summary: As the field of quantum computing progresses to larger-scale devices, multiplexing will be crucial to scale quantum processors. While multiplexed readout is common practice for superconducting devices, relatively little work has been reported about the combination of flux and microwave control lines. Here, we present a method to integrate a microwave line and a flux line into a single “XYZ line.” This combined control line allows us to perform fast single-qubit gates as well as to deliver flux signals to the qubits. The measured relaxation times of the qubits are comparable to state-of-the-art devices employing separate control lines. We benchmark the fidelity of single-qubit gates with randomized benchmarking, achieving a fidelity as high as 99.93±0.04%, and we demonstrate that XYZ lines can in principle be used to run parametric entangling gates. URL: https://aip.scitation.org/doi/abs/10.1063/5.0065517 Title: Parametric-Resonance Entangling Gates with a Tunable Coupler Source: Phys. Rev. Applied 16, 024050 Summary: High-fidelity parametric gates have been demonstrated with superconducting qubits via rf flux modulation of the qubit frequency. The modulation however leads to renormalization of the bare qubit-qubit coupling, thereby reducing the gate speed. Here, we realize a parametric-resonance gate, which is activated by bringing the average frequency of the modulated qubit in resonance with a static-frequency qubit while approximately retaining the bare qubit-qubit coupling. The activation of parametric-resonance gates does not depend on the frequency of modulation, allowing us to choose the modulation frequencies and avoid frequency collisions. Moreover, we show that this approach is compatible with tunable coupler architectures, which reduce always-on residual couplings. Using these techniques, we demonstrate iSWAP and controlled-Z gates between two qubits coupled via a tunable coupler with average process fidelities as high as 99.3% and 97.9%, respectively. The flexibility in activating parametric-resonance gates combined with a tunable coupler architecture provides a pathway for building large-scale quantum computers. URL: https://journals.aps.org/prapplied/abstract/10.1103/PhysRevApplied.16.024050 Title: Floating Tunable Coupler for Scalable Quantum Computing Architectures Source: Phys. Rev. Applied 15, 064063 Summary: We propose a floating tunable coupler that does not rely on direct qubit-qubit coupling capacitances to achieve the zero-coupling condition. We show that the polarity of the qubit-coupler couplings can be engineered to offset the otherwise constant qubit-qubit coupling and attain the zero-coupling condition when the coupler frequency is above or below the qubit frequencies. We experimentally demonstrate these two operating regimes of the tunable coupler by implementing symmetric and asymmetric configurations of the superconducting pads of the coupler with respect to the qubits. Such a floating tunable coupler provides flexibility in designing large-scale quantum processors while reducing the always-on residual couplings. URL: https://journals.aps.org/prapplied/abstract/10.1103/PhysRevApplied.15.064063 Title: Scalable Quantum Circuit and Control for a Superconducting Surface Code Source: Phys. Rev. Applied 8, 034021 Summary: We present a scalable scheme for executing the error-correction cycle of a monolithic surface-code fabric composed of fast-flux-tunable transmon qubits with nearest-neighbor coupling. An eight-qubit unit cell forms the basis for repeating both the quantum hardware and coherent control, enabling spatial multiplexing. This control uses three fixed frequencies for all single-qubit gates and a unique frequency-detuning pattern for each qubit in the cell. By pipelining the interaction and readout steps of ancilla-based X- and Z-type stabilizer measurements, we can engineer detuning patterns that avoid all second-order transmon-transmon interactions except those exploited in controlled-phase gates, regardless of fabric size. Our scheme is applicable to defect-based and planar logical qubits, including lattice surgery. URL: https://journals.aps.org/prapplied/abstract/10.1103/PhysRevApplied.8.034021 Title: Detecting bit-flip errors in a logical qubit using stabilizer measurements Source: Nature Communications 6:6983 (2015) Summary: None URL: http://www.nature.com/ncomms/2015/150429/ncomms7983/abs/ncomms7983.html Title: Entanglement of two superconducting qubits in a waveguide cavity via monochromatic two-photon excitation Source: Physical Review Letters 109, 240505 (2012) Summary: We report a system where fixed interactions between noncomputational levels make bright the otherwise forbidden two-photon 00-->11 transition. The system is formed by hand selection and assembly of two discrete component transmon-style superconducting qubits inside a rectangular microwave cavity. The application of a monochromatic drive tuned to this transition induces two-photon Rabi-like oscillations between the ground and doubly excited states via the Bell basis. The system therefore allows all-microwave two-qubit universal control with the same techniques and hardware required for single qubit control. We report Ramsey-like and spin echo sequences with the generated Bell states, and measure a two-qubit gate fidelity of 90% (unconstrained) and 86% (maximum likelihood estimator). URL: https://journals.aps.org/prl/abstract/10.1103/PhysRevLett.109.240505 | S29: Title: Method for executing a quantum error correction cycle in a quantum computer Issuer: US 11194659 Issued On: Dec 7, 2021 Description: None Title: Superconducting quantum circuit having a resonant cavity thermalized with metal components Issuer: US 8841764 Issued On: Sep 23, 2014 Description: None Title: Improved qubit designs for quantum circuits Issuer: US 16651529 Issued On: Aug 20, 2020 Description: None Title: Controlling a Tunable Floating Coupler Device in a Superconducting Quantum Processing Unit Issuer: 17901633 Issued On: None Description: None | V29: Title: Director, Quantum Engineering Company: None Start At: None Ends At: None Location: None Description: None Title: Senior Manager, Quantum Engineering Company: None Start At: None Ends At: None Location: None Description: None Title: Lead Quantum Engineer Company: None Start At: None Ends At: None Location: None Description: None Title: Senior Quantum Engineer Company: None Start At: None Ends At: None Location: None Description: None Title: Postdoctoral researcher Company: None Start At: None Ends At: None Location: None Description: None Title: Postdoctoral researcher Company: None Start At: None Ends At: None Location: None Description: None Title: Postdoctoral researcher Company: None Start At: None Ends At: None Location: None Description: None Title: Postdoctoral researcher Company: None Start At: None Ends At: None Location: None Description: None | W29: School: Università degli studi Roma TRE Degree: Doctor of Philosophy (Ph.D.), Physics Activities: None School: Università degli Studi di Padova Degree: Degree in Physics Activities: None | X29: I have twenty years of experimental research and path-finding in quantum computing with superconducting qubits, ten years of which in the industrial quantum computing sector covering roles from individual contributor to director of quantum engineering. | Y29: Director, Quantum Engineering at Rigetti Computing | Z29: Stefano_Poletto.png
A30: Mohammad Javad Naderi | C30: https://www.linkedin.com/in/mjnaderi | D30: 618 | F30: Co-founder and Software Engineer | G30: Quera | H30: IT Services and IT Consulting | I30: https://www.linkedin.com/redir/suspicious-page?url=https%3A%2F%2Fquera%2eir%2F | J30: https://www.linkedin.com/company/quera/ | L30: 51-200 | M30: 10 yrs 9 mos | N30: Iran | O30: Iran | P30: English, Persian | V30: Title: Co-founder and Software Engineer Company: None Start At: None Ends At: None Location: None Description: None Title: Software Developer Company: None Start At: None Ends At: None Location: None Description: None | W30: School: Sharif University of Technology Degree: Master’s Degree, Computer Software Engineering Activities: None School: Sharif University of Technology Degree: Bachelor’s Degree, Computer Software Engineering Activities: None School: Shahid Beheshti Highschool, Shahrekord Degree: High School, Mathematics Activities: None | Y30: CTO at Quera
A31: Tyler Wilson | B31: Tyler Wilson.png | C31: https://www.linkedin.com/in/tyler-wilson-phd | D31: 821 | F31: Senior Software Engineer, Quantum Algorithms and Applications | G31: Rigetti Computing | H31: IT Services and IT Consulting | I31: http://rigetti.com | J31: https://www.linkedin.com/company/rigetti-computing/ | L31: 51-200 | M31: 3 yrs 6 mos | N31: Canada | O31: Grimsby, Ontario | Q31: Title: Stabilization of the Lattice Boltzmann Method Using Information Theory Source: arXiv Summary: A novel Lattice Boltzmann method is derived using the Principle of Minimum Cross Entropy (MinxEnt) via the minimization of Kullback-Leibler Divergence (KLD). By carrying out the actual single step Newton-Raphson minimization (MinxEnt-LBM) a more accurate and stable Lattice Boltzmann Method can be implemented. To demonstrate this, 1D shock tube and 2D lid-driven cavity flow simulations are carried out and compared to Single Relaxation Time LBM, Two Relaxation Time LBM, Multiple Relaxation Time LBM and Eherenfest Step LBM. URL: https://arxiv.org/abs/1801.03863 Title: Barkas effect in stopping of fast diclusters in solids. Source: Radiation Effects and Defects in Solids Summary: We study the stopping of a fast proton dicluster moving through a metal target with an electron gas described by a hydrodynamic model. Both the first-order and the second-order expressions are derived and computed for the total stopping force on the cluster, giving a nonlinear correction of the Barkas type. Results are shown as functions of the cluster speed and the interproton distance in the cases of a randomly oriented dicluster and a colinear dicluster consisting of two protons aligned in the direction of motion. We find that the Barkas correction increases the overall stopping force, especially at lower speeds and shorter interproton distances. While the Barkas correction is found to accentuate interferences in the vicinity effect for colinear diclusters, it presents an insignificant contribution to the vicinity effect for randomly oriented diclusters. URL: https://www.tandfonline.com/doi/abs/10.1080/10420150.2015.1137918 Title: Feedback action of vicinage eect in cluster stopping via nonhomogeneous charge reduction. Source: Physical Review A Summary: We use a self-consistent, variational-statistical approach to analyze the vicinage effect on charge states of constituent ions in fast large clusters, passing through thin foils. The solutions of the resulting nonlinear integral equation show that the individual ion charges are reduced in comparison to isolated isotachic ions and are distributed nonhomogeneously throughout the cluster. Using a statistical description of the ion positions in conjunction with the nonhomogeneous distribution of ion charges, we evaluate the total stopping power of the cluster by means of the dielectric formalism. It is shown that interference in cluster stopping coming from the spatial correlations among the constituent ions is strongly influenced by the vicinage effect on ion charge states. URL: https://journals.aps.org/pra/abstract/10.1103/PhysRevA.67.022903 | V31: Title: Senior Software Engineer, Quantum Algorithms and Applications Company: None Start At: None Ends At: None Location: None Description: None Title: Co-Founder, Models and Algorithms Company: None Start At: None Ends At: None Location: None Description: None Title: Data Scientist Company: None Start At: None Ends At: None Location: None Description: None Title: Risk Modelling Researcher Company: None Start At: None Ends At: None Location: None Description: None Title: Sessional Lecturer Company: None Start At: None Ends At: None Location: None Description: None Title: Industry Liaison Officer and Managing Editor Company: None Start At: None Ends At: None Location: None Description: None Title: Vice President - Technology Company: None Start At: None Ends At: None Location: None Description: None Title: Research Scientist Company: None Start At: None Ends At: None Location: None Description: None | W31: School: University of Toronto Degree: Doctor of Philosophy (Ph.D.), Mathematics Activities: None School: University of Waterloo Degree: M.Math, Applied Mathematics Activities: None School: University of Waterloo Degree: B.Sc, Honours Physics Activities: None School: University of Waterloo Degree: B.Math, Honours Applied Mathematics Activities: None | X31: Mathematics PhD with broad expertise in many quantitative methods including machine learning, simulation, analysis, quantum computing, and computational statistics. Proficient in programming languages such as Python, Matlab; experience in OpenCL, C++, JavaScript; platforms such as AWS, TensorFlow, Git, SAS; databases such as MongoDB and SQL; applications such as TeX, LaTeX, BibTeX, Microsoft Office. Extensive leadership and entrepreneurial experience with exceptionally strong communication skills. I am currently using this skill set as a Senior Software Engineer (Quantum Algorithms and Applications) at Rigetti Computing. I have also developed and tested machine learning models as a Data Scientist at BioSymetrics, led model development at Tesseraqt Optimization, and carried out research as a risk management quant at CIBC. In many of my roles I have consulted with top decision makers at companies to help them navigate emerging technologies such as machine learning, quantum computing, and quantitative finance. When presented with a business challenge, I have experience at all stages of the solution stack from delivering talent and funding, to project management, computer/machine learning model design, implementation, and testing. | Y31: Mathematics | Quantum Computing | Data Science | Software Engineering | Quantitative Analysis | Z31: Tyler_Wilson,_PhD.png
A32: Lucy Linthwaite | B32: Lucy Linthwaite.png | C32: https://www.linkedin.com/in/lucy-linthwaite-45760010 | D32: 1850 | E32: lucy.linthwaite@uk.ibm.com | F32: Director, UK&I Communications and Global Comms Intelligence | G32: IBM | H32: IT Services and IT Consulting | I32: http://www.ibm.com | J32: https://www.linkedin.com/company/ibm/ | L32: 10001-0 | M32: 11 mos | N32: United Kingdom | O32: Greater London, England | V32: Title: Director, UK&I Communications and Global Comms Intelligence Company: None Start At: None Ends At: None Location: None Description: None Title: Director, Global Communications Strategy and Activation Company: None Start At: None Ends At: None Location: None Description: None Title: Brand, Communications and Social Leader, EMEA Company: None Start At: None Ends At: None Location: None Description: None Title: Global Campaign Geo Communications Leader Company: None Start At: None Ends At: None Location: None Description: None Title: External Communications Leader Company: None Start At: None Ends At: None Location: None Description: None Title: External Media Relations Manager Company: None Start At: None Ends At: None Location: None Description: None Title: Senior PR & Communications Officer Company: None Start At: None Ends At: None Location: None Description: None Title: PR Account Manager Company: None Start At: None Ends At: None Location: None Description: None Title: PR & Communications Executive Company: None Start At: None Ends At: None Location: None Description: None | W32: School: London Metropolitan University Degree: Bachelor of Science (BSc) Hons, Social Policy and Management Activities: None | X32: Senior communications executive with over two decades of experience across agency and in-house roles, advising UK and global public companies as well as private partnerships in multiple industries. Helping to scale reputation and market presence. Proven leader of country and international teams, delivering UK, European, and global creative campaigns for high-profile B2C and B2B brands. Extensive experience protecting and enhancing reputations across a range of channels including media, social, and employee communications. Skilled in developing compelling strategies and narratives that build executive visibility, drive organisational change, and launch cutting-edge innovations. Beyond my day job, I play an active role in the wider communications industry. I’ve proudly served as a judge for the PR Moment Awards for five years and have also judged the AMEC Awards. A keen public speaker and always up for a challenge, I regularly share my experience and ideas at industry events including PR Week PR360, PR Week B2B Summit, PR Week Measurement Conference, AMEC Measurement Month, CommsCon X Insights, PR Moment conferences, and The Richmond Communication Directors’ Forum. | Y32: Director, UK&I Communications and Global Comms Intelligence, IBM | Z32: Lucy_Linthwaite.png
A33: Guido Somers | C33: https://www.linkedin.com/in/guido-somers-876a043 | D33: 3243 | E33: guido.somers@ibm.com | F33: CTO & Chief Architect Europe | G33: IBM | H33: IT Services and IT Consulting | I33: http://www.ibm.com | J33: https://www.linkedin.com/company/ibm/ | L33: 10001-0 | M33: 9 yrs 3 mos | N33: Switzerland | O33: Montreux, Vaud | P33: Dutch, English | Q33: Title: IBM Power E1050: Technical Overview and Introduction Source: IBM ITSO - REDP-5684-00 (ISBN-13: 9780738460772) Summary: This IBM® Redpaper publication is a comprehensive guide that covers the IBM Power E1050 server (9043-MRX) that uses the latest IBM Power10 processor-based technology and supports IBM AIX® and Linux operating systems (OSs). The goal of this paper is to provide a hardware architecture analysis and highlight the changes, new technologies, and major features that are being introduced in this system URL: https://www.redbooks.ibm.com/abstracts/redp5684.html Title: IBM PowerVM Live Partition Mobility Source: IBM ITSO - SG24-7460-01 Summary: Live Partition Mobility is the next step in the IBMs Power Systems™ virtualization continuum. It can be combined with other virtualization technologies, such as logical partitions, Live Workload Partitions, and the SAN Volume Controller, to provide a fully virtualized computing platform that offers the degree of system and infrastructure flexibility required by today's production data centers. URL: http://w3.itso.ibm.com/abstracts/sg247460.html?Open Title: IBM System p520 Technical Overview and Introduction Source: IBM ITSO - REDP-4403-00 Summary: This IBM Redpaper publication is a comprehensive guide covering the IBM Power 520 server, machine type model 8203-E4A. The goal of this paper is to introduce this innovative server that includes IBM System i and IBM System p and new hardware technologies. URL: http://w3.itso.ibm.com/abstracts/redp4403.html?Open Title: IBM System p550 Technical Overview and Introduction Source: IBM ITSO - REDP-4404-00 Summary: This IBM® Redpaper™ is a comprehensive guide covering the Power 550 server. The goal of this paper is to introduce the innovative Power 550. It introduces major hardware offerings and discusses their prominent functions. The Redpaper expands the current set of IBM System p documentation by providing a desktop reference that offers a detailed technical description of the 550 system. URL: http://w3.itso.ibm.com/abstracts/redp4404.html?Open Title: IBM System p570 Technical Overview and Introduction Source: IBM ITSO - REDP-4405-00 Summary: This IBM® Redpaper is a comprehensive guide covering the IBM System p 570 UNIX® server. The goal of this paper is to open the doors to the innovative IBM System p 570. It introduces major hardware offerings and discusses their prominent functions. URL: http://w3.itso.ibm.com/redpieces/abstracts/redp4405.html?Open Title: IBM System p Partition Mobility Source: IBM ITSO - SG24-7460 Summary: This was the original Live Partition Mobility book and was superseded in 2008 by "IBM PowerVM Live Partition Mobility - IBM ITSO - SG24-7460-01" http://w3.itso.ibm.com/abstracts/sg247460.html?Open URL: None Title: Integrated Virtualization Manager on IBM System p5 Source: IBM ITSO - REDP-4061-01 (2006) (this has been superseded in 2012 by another version (REDP-4061-02) with different authors Summary: The Virtual I/O Server (VIOS) is part of the IBM PowerVM® feature on IBM® Power Systems™ and part of the IBM POWER® Hypervisor™. The VIOS is also supported on IBM BladeCenter®. The server is a single-function appliance that is in the logical partition (LPAR) of the Power Systems server. The VIOS facilitates the sharing of physical I/O resources between client partitions (IBM AIX®, IBM i, and Linux) within the server. The Virtual I/O Server provides a virtual SCSI target, N_Port ID Virtualization (NPIV) target, and Shared Ethernet Adapter (SEA) virtual I/O function to client LPARs. The Virtual I/O Server has the capability of a hardware management function, the Integrated Virtualization Manager (IVM). IVM is a simplified hardware management solution that inherits most of the Hardware Management Console (HMC) features. The console manages a single server, avoiding the need of a dedicated personal computer. This device is designed to provide a solution that enables the administrator to reduce system setup time and to make hardware management easier, at a lower cost. URL: http://w3.itso.ibm.com/abstracts/redp4061.html?Open | V33: Title: CTO & Chief Architect Europe Company: None Start At: None Ends At: None Location: None Description: None Title: Executive IT Architect & Global Technical Leader Nestlé Company: None Start At: None Ends At: None Location: None Description: None Title: Enterprise Infrastructure Architect / CTO FSS - CITA Company: None Start At: None Ends At: None Location: None Description: None Title: Global ISV Solution Architect Company: None Start At: None Ends At: None Location: None Description: None Title: Systems Architect Company: None Start At: None Ends At: None Location: None Description: None Title: Programmer/Analyst Company: None Start At: None Ends At: None Location: None Description: None Title: Adjunct Director Heavy Metals Company: None Start At: None Ends At: None Location: None Description: None Title: Researcher Theoretical Physics Company: None Start At: None Ends At: None Location: None Description: None | W33: School: VLEKHO Business School Brussel Degree: Business Administration and Management, General Activities: None School: University of Antwerp Degree: Master of Science (MSc), Physical Chemistry Activities: None School: Ghent University Degree: Master of Science (MSc), Chemistry Activities: None School: University of Antwerp Degree: Master of Science (MSc), Biotechnology Activities: None School: Rijksuniversitair Centrum Antwerpen (RUCA) - State Universitary Center Antwerp Degree: Electronics Activities: None School: Sint-Jan Berchmanscollege Degree: Scientific A - Mathematics Activities: None | X33: CTO Europe & Chief Architect within IBM Global Delivery carrying end-to-end responsibility for all Data Center and Cloud Migration engagements across Europe. Currently leading the European team of 70+ Chief Migration Architects. A senior certified Executive IT Architect with a wide range of experience in both the Financial Services Sector as in CPG/FMCG. Trusted advisor and leader providing proactive technical counsel to CIO, CTO and other key IT executives on technical strategy and innovation, direction and projects (cognitive, big data, cloud, security, Blockchain, IoT). Improve and broaden client access to IBM’s global technical and innovation expertise. Increase the value that clients derive from application of new and existing technologies and accelerate innovation. Provide architectural thought leadership based on the client's business need. More than 20 years of IT business experience with a broad spectrum of technical (cross-platform hardware, software and services) and leadership skills. International experience through projects and assignments. Acting as thought leader within different technical and industry specific communities (FSS & CPG). Acknowledged technical leader in several domains like complex IT infrastructures, Business Analytics, Cloud, DC Optimization and ISV Solutions (SAP & Oracle). Member and founder of several technical expert communities of practice within IBM. Author of multiple technical publications on virtualization and infrastructure (Platinum Redbook Author). Mentoring people around the world on profession and career aspects. Specialties:Architectural creativity in competitive sales situations, leading sales teams to deliver innovative solutions, enterprise architecture, analytical skills for business and technical problems, infrastructure solution design, broad and deep architectural and technical skill set, client partnering, first of a kind implementations. | Y33: CTO & Chief Architect Europe - Cloud - Global Delivery
A34: Nicholas (Nick) A. Wong | B34: Nicholas (Nick) A. Wong.png | C34: https://www.linkedin.com/in/nicholasawong | D34: 1421 | E34: nwong@us.ibm.com | F34: IBM Director, Data Platform Sales (US West Horizon Market) | G34: IBM | H34: IT Services and IT Consulting | I34: http://www.ibm.com | J34: https://www.linkedin.com/company/ibm/ | L34: 10001-0 | M34: 3 mos | N34: United States | O34: San Francisco, California | U34: Name: TLC Leaders Program Certificate of Completion Authority: The Leadership Consortium (TLC) Date: 2023-11 URL: https://linkedin.com/company/33283990 | V34: Title: IBM Director, Data Platform Sales (US West Horizon Market) Company: None Start At: None Ends At: None Location: None Description: None Title: IBM Chief of Staff to Dinesh Nirmal (IBM Senior Vice President, Products, IBM Software) Company: None Start At: None Ends At: None Location: None Description: None Title: IBM Manager, Data, AI, & Automation Sales, US West Company: None Start At: None Ends At: None Location: None Description: None Title: IBM Partner Account Manager (Technology Partner Seller) Company: None Start At: None Ends At: None Location: None Description: None Title: IBM Ecosystem Market Leader, US Industrial Market Company: None Start At: None Ends At: None Location: None Description: None Title: IBM Manager, Digital Sales, Watson Internet of Things (Connected Ops & Continuous Engineering) Company: None Start At: None Ends At: None Location: None Description: None Title: IBM Manager, Digital Sales, Watson Internet of Things - Connected Operations Company: None Start At: None Ends At: None Location: None Description: None Title: IBM Industry Client Leader - Communications / CSI Market Segment Company: None Start At: None Ends At: None Location: None Description: None Title: IBM Client Executive - Communications / CSI Market Segment Company: None Start At: None Ends At: None Location: None Description: None Title: IBM Client Executive - Northern California Enterprise Business Unit Company: None Start At: None Ends At: None Location: None Description: None Title: IBM Client Executive - Northern California Enterprise Business Unit Company: None Start At: None Ends At: None Location: None Description: None Title: IBM Client Executive - Northern California Enterprise Business Unit Company: None Start At: None Ends At: None Location: None Description: None Title: IBM Client Executive - Northern California Enterprise Business Unit Company: None Start At: None Ends At: None Location: None Description: None Title: IBM Client Executive - General Business Company: None Start At: None Ends At: None Location: None Description: None Title: IBM Client Executive - General Business Company: None Start At: None Ends At: None Location: None Description: None Title: MBA Candidate, 2010 Company: None Start At: None Ends At: None Location: None Description: None Title: Intern - Web Presence Engagement Services, Internet Services Group Company: None Start At: None Ends At: None Location: None Description: None Title: Competitive OI Specialist: Northern California Sales Company: None Start At: None Ends At: None Location: None Description: None | W34: School: University of California, Davis - Graduate School of Management Degree: Master of Business Administration (M.B.A.), High Technology and General Management Activities: None School: University of California, Merced Degree: Bachelor’s Degree, Management, Cognitive Science Activities: None School: California High School (San Ramon, CA) Degree: High School Activities: None | X34: Responsible for leading a team of (55) sellers (both Brand and Technical) focused on selling IBM's Data Platform portfolio to a set of (115) high-priority clients in the US West, across all Market industries. In a world of AI, IBM's Data Platform portfolio is more relevant than ever to an Enterprise. Agents, Models, etc. are only as powerful as the tools behind them - with Data being the most important of those tools. IBM’s Data Platform story is the evolution from fragmented, siloed data to a unified, open, hybrid data fabric that powers AI, analytics, and regulated workloads while delivering governance, security, and cost‑effective scalability. • Industry experience: Industrial, Communications / CSI & CSP, Distribution, Public, and Financial Services. • IBM First Line Manager (FLM), Second Line Manager (SLM), and Executive experience. • Completed IBM's 2010 SUMMIT Program / Global Sales School, graduating with Distinction. • MBA Graduate from UC Davis' Graduate School of Management (June 2010) with an emphasis on General Management and High Technology. • Completed Undergraduate at UC Merced (December 2007) with a B.S. in Management and a Minor in Cognitive Science. | Y34: IBM Director, Data Platform Sales (US West Horizon Market) | Z34: Nicholas_(Nick)_A._Wong.png
A35: Krystian Mołdoch | B35: Krystian Mołdoch.png | C35: https://www.linkedin.com/in/krystianmoldoch | D35: 480 | F35: Director, Global Clinical Solutions | G35: AstraZeneca | H35: Pharmaceutical Manufacturing | I35: http://www.astrazeneca.com | J35: https://www.linkedin.com/company/astrazeneca/ | L35: 10001-0 | M35: 1 yr 9 mos | N35: Poland | O35: Warsaw Metropolitan Area | P35: english, polish | V35: Title: Director, Global Clinical Solutions Company: None Start At: None Ends At: None Location: None Description: None Title: Associate Director, Global Clinical Solutions Company: None Start At: None Ends At: None Location: None Description: None Title: Global Clinical Solutions Manager Company: None Start At: None Ends At: None Location: None Description: None Title: Processes & Enabling Solutions Specialist Company: None Start At: None Ends At: None Location: None Description: None Title: Clinical Operations Enablement Associate Company: None Start At: None Ends At: None Location: None Description: None Title: Clinical Operations Enablement Assistant Company: None Start At: None Ends At: None Location: None Description: None | W35: School: University of Warsaw Degree: Master of Science - MS, Chemistry Activities: None School: University of Warsaw Degree: Bachelor of Science - BS, Chemistry Activities: None | Y35: Director, Global Clinical Solutions w AstraZeneca | Z35: Krystian_Mołdoch.png
A36: Ronnie Choudhary | B36: Ronnie Choudhary.png | C36: https://www.linkedin.com/in/ronnie-choudhary-b66a2b4 | D36: 4926 | E36: ronnie.choudhary@astrazeneca.com | F36: Group Director, Marketing and Customer Experience Analytics, Oncology | G36: AstraZeneca | H36: Pharmaceutical Manufacturing | I36: http://www.astrazeneca.com | J36: https://www.linkedin.com/company/astrazeneca/ | L36: 10001-0 | M36: 3 mos | N36: United States | O36: Washington, District of Columbia | P36: Bengali, English | S36: Title: Mathematical models for predicting shopper traffic at a shopper region useful for developing inter alia a metric for measuring impressions to in-store advertising Issuer: US US 7996256 Issued On: Aug 9, 2011 Description: None | T36: Title: Advisory Board Member - Google Consumer Survey Start At: 01/2012 Ends At: 2015 Company: Google Cause: Science_and_technology Description: Google Consumer Surveys is a fast, affordable, and accurate market research tool that helps you make informed business decisions by asking internet and mobile users survey questions. Users complete survey questions in order to access high-quality content or Google Play store credit. Google automatically aggregates and analyzes responses through a simple online interface. http://www.google.com/insights/consumersurveys/advisory_board Title: Board of Trustee Start At: 09/2012 Ends At: Present Company: MidPointe Library System Cause: Education Description: MidPointe Library System takes pride in being connected to community at the grass-root level and help the children and citizens become productive, by providing information and research services in an inviting atmosphere. The MidPointe Library System serves the cities of Middletown, Trenton, and Monroe and the townships of West Chester, Liberty, Lemon, Madison, and Wayne. The MidPointe Library System offers locations in Middletown, Monroe, Trenton and West Chester. Title: Volunteer Annual Summits Start At: 01/2010 Ends At: 2015 Company: MATHCOUNTS Foundation Cause: Education Description: Volunteer in conducting Math Counts Annual Meets, tests and competition. Grade and counsel Math and Science Middle School Teachers. Title: Board of Trustee Start At: 02/2015 Ends At: 2017 Company: Marketing Science Institute Cause: Education Description: The MSI mission is to bring the best of science to the complex world of marketing. Through high-quality events and activities, cutting-edge content and publications, and productive networking opportunities, MSI members stay on the forefront of marketing thought and practice. MSI is an indispensable means to enhance professional development and improve marketing decision making for each of its members and member organizations. Founded in 1961, the Marketing Science Institute is a nonprofit, membership-based organization dedicated to bridging the gap between academic marketing theory and business practice. MSI is unique as the only research-based organization with an expansive network of practically-minded marketing academics from the best business schools all over the world as well as thoughtful practitioners from 70+ leading companies. Title: Co-Chair of the Board of Advisors Start At: 07/2024 Ends At: Present Company: MidPointe Library System Cause: Education Description: Fundraising, Networking, Middletown Community Foundation and STEM Education | U36: Name: Predictive Customer Analytics Authority: LinkedIn Date: 2025-9 URL: https://linkedin.com/company/1337 Name: Market Research: Quantitative Authority: LinkedIn Date: 2025-6 URL: https://linkedin.com/company/1337 | V36: Title: Group Director, Marketing and Customer Experience Analytics, Oncology Company: None Start At: None Ends At: None Location: None Description: None Title: Sr. Director, Advanced Analytics | Marketing and Customer Experience Company: None Start At: None Ends At: None Location: None Description: None Title: Sr. Director, Strategy, Insights and Analytics Company: None Start At: None Ends At: None Location: None Description: None Title: Senior Director, Global Customer Strategy Company: None Start At: None Ends At: None Location: None Description: None Title: Director, Customer Strategy & Advanced Analytics Lead (EU); Company: None Start At: None Ends At: None Location: None Description: None Title: Management and Brand Consulting at Accenture Interactive Company: None Start At: None Ends At: None Location: None Description: None Title: Director Company: None Start At: None Ends At: None Location: None Description: None Title: Strategic Marketing Specialist Company: None Start At: None Ends At: None Location: None Description: None Title: Consultant Company: None Start At: None Ends At: None Location: None Description: None | W36: School: Indian Institute of Technology (Banaras Hindu University), Varanasi Degree: B.Tech., Computer Science & Engineering Activities: None School: University of Arizona Degree: Master of Business Administration - MBA Activities: None School: University of Arizona Degree: Business Administration and Management, General Activities: None School: University of Arizona - Eller College of Management Degree: Master of Business Administration (MBA), Marketing Activities: None | X36: Seasoned executive with global leadership experience leading strategy, advanced analytics, insights and research methods to execute growth strategies - across consumer, market, retail and omni-channels. Proven expertise in improving marketing, content & communication, and launch strategies leveraging advanced research techniques from traditional qualitative approaches to cutting-edge applied analytics and intelligence (AI, ML enabled text analytics). Expanse of experience delivering solutions across multinational markets for Global 100 companies utilizing innovative algorithms, advanced statistical models and data science techniques. Research expertise in activating digital, mobile and e-commerce channels. Integrated marketing communication/media mix planning, campaign management, customer relationship marketing, marketing ROI, reporting, KPIs & dashboards, financial modeling of marketing efficiency & effectiveness, budget, portfolio allocation and optimization. | Y36: AI driven Strategy, Insights, Smart Analytics, Change Agent: Procter & Gamble, Pfizer, Accenture, Samsung, Novartis | Z36: Ronnie_Choudhary.png
A37: Álex Turpin | B37: Álex Turpin.png | C37: https://www.linkedin.com/in/alejandroturpin | D37: 3175 | F37: Senior Director | AI Governance R&D | G37: AstraZeneca | H37: Pharmaceutical Manufacturing | I37: http://www.astrazeneca.com | J37: https://www.linkedin.com/company/astrazeneca/ | L37: 10001-0 | M37: 3 mos | N37: Spain | O37: Spain | P37: Catala, Deutsch | U37: Name: Quality Management System - Medical Devices - ISO 13485 Authority: Complear Academy Date: Unknown URL: None Name: ”la Caixa” Foundation Fellows Authority: Fundación ”la Caixa” Date: Unknown URL: https://linkedin.com/company/546456 | V37: Title: Senior Director | AI Governance R&D Company: None Start At: None Ends At: None Location: None Description: None Title: Director, Commercial IT & Digital - AI Capability International Company: None Start At: None Ends At: None Location: None Description: None Title: Expert Partner - Artificial Intelligence & Data Science Company: None Start At: None Ends At: None Location: None Description: None Title: Head of Data Science & AI → Head of Product Engineering & Delivery Company: None Start At: None Ends At: None Location: None Description: None Title: Founder & CEO Company: None Start At: None Ends At: None Location: None Description: None Title: Principal Investigator & PhD in Physics (Machine Learning & Computational Science) Company: None Start At: None Ends At: None Location: None Description: None | W37: School: GBSB Global Business School Degree: G-Accelerator Program, Business Activities: None School: Universitat Autònoma de Barcelona Degree: Doctor of Philosophy (PhD), Physics Activities: None School: Universitat Politècnica de Catalunya Degree: MSc In Photonics, Photonics Activities: None School: Universitat Autònoma de Barcelona Degree: Bachelor's degree, Physics Activities: None School: Universitat Autònoma de Barcelona Degree: Doctor of Philosophy - PhD, Physics Activities: None | X37: I design and scale AI systems in research-driven environments, where scientific ambition, speed of innovation and governance must coexist. For a long time, I saw governance as many technical teams do: as a necessary constraint, something to comply with once the real work was done. Experience has changed that view. Today, my work focuses on embedding governance into the design of AI systems and programmes: not as a control layer, but as an enabler of better decisions, faster alignment and trusted innovation in R&D. My career sits at the intersection of four domains that rarely coexist in one profile: deep science, machine learning and data science, innovation and leadership, and AI governance in highly regulated R&D environments. This combination allows me to bridge cutting-edge research, technical excellence and organisational decision-making. Currently, as Senior Director of AI Governance (R&D) at AstraZeneca, I lead the strategy and adoption of AI governance across global R&D, supporting the responsible and scalable use of AI in scientific research and development programmes. Earlier in my career, I co-founded a deep tech startup, built machine learning systems, led engineering and data science teams, and worked across physics and neuroscience. This gives me a first-hand understanding of how AI moves from research to real-world deployments well as where it often breaks down. I’m particularly interested in how organisations make decisions around complex AI systems, how governance can act as an enabler rather than a constraint, and how innovation can scale responsibly in research-driven environments. If you’re working at the intersection of AI, science and innovation, feel free to connect. | Y37: AI & Deep Tech Leader | Senior Director, AI Governance in R&D | Designing AI systems where governance accelerates innovation | Z37: Álex_Turpin,_PhD.png
A38: Kim Hardman | B38: Kim Hardman.png | C38: https://www.linkedin.com/in/kim-hardman-3ba5a92a | D38: 4312 | F38: Director UK Apprenticeships | G38: AstraZeneca | H38: Pharmaceutical Manufacturing | I38: http://www.astrazeneca.com | J38: https://www.linkedin.com/company/astrazeneca/ | L38: 10001-0 | M38: 4 yrs | N38: United Kingdom | O38: Macclesfield, England | V38: Title: Director UK Apprenticeships Company: None Start At: None Ends At: None Location: None Description: None Title: Associate Director & UK Apprenticeships Lead Company: None Start At: None Ends At: None Location: None Description: None Title: UK Apprentice Programme Manager - AstraZeneca Company: None Start At: None Ends At: None Location: None Description: None Title: Global Emerging Talent Recruitment Manager Company: None Start At: None Ends At: None Location: None Description: None Title: HR Business Partner - Science Units, UK Sites (interim) Company: None Start At: None Ends At: None Location: None Description: None Title: Global Resourcing Partner Company: None Start At: None Ends At: None Location: None Description: None Title: Global Talent Management Co-ordinator Company: None Start At: None Ends At: None Location: None Description: None | W38: School: Manchester Institute for Psychotherapy Degree: Diploma, Transactional Analysis Psychotherapy Activities: None | X38: As Director of Apprenticeships at AstraZeneca, I work across all functions to identify Apprentice opportunities to support our early talent pipeline, including the recruitment of early careers and upskilling our existing workforce. I have designed an approach to ensure that all our programmes provide an excellent opportunity for Apprentices to gain a great experience, supporting them whilst they learn within their roles. I am passionate about Apprenticeships and how they can support our organisation and have seen the breadth and depth of our apprenticeship programme grow significantly in recent years as awareness in our business increases. I work to prioritise the enhancement of our reputation in the UK Scientific and Business Community, through the delivery of a linked programme of activities to support access to relevant skills. | Y38: Director of Apprenticeships - AstraZeneca | Z38: Kim_Hardman.png
A39: Nathan Schoenkin | B39: Nathan Schoenkin.png | C39: https://www.linkedin.com/in/nathanschoenkin | D39: 1298 | E39: nathan@schoenkin.fr | F39: Associate Director of Business Continuity & Crisis Management | G39: AstraZeneca | M39: 2 yrs 5 mos | N39: United States | O39: United States | P39: English, French | Q39: Title: Enhancing operational resilience through situational awareness in business continuity Source: The BCI Summary: Nathan examines operational resilience based upon experience within the critical infrastructure and pharmaceutical sectors. While monitoring internal risks is a critical part of business continuity, this article explores how situational awareness can improve the understanding of risks external to the organization. URL: https://www.thebci.org/news/enhancing-operational-resilience-through-situational-awareness-in-business-continuity.html | U39: Name: FBCI Authority: The BCI Date: 2025-8 URL: https://linkedin.com/company/1022236 Name: Certificate in Cyber Security Policy Authority: University of Maryland Global Campus Date: Unknown URL: https://linkedin.com/company/9375 | V39: Title: Associate Director of Business Continuity & Crisis Management Company: None Start At: None Ends At: None Location: None Description: None Title: Leader of the Operational Resilience SIG Company: None Start At: None Ends At: None Location: None Description: None Title: Committe Member of Operational Resilience SIG Company: None Start At: None Ends At: None Location: None Description: None Title: BCI Awards Judge Company: None Start At: None Ends At: None Location: None Description: None Title: Business Continuity Program Manager Company: None Start At: None Ends At: None Location: None Description: None Title: Senior Resilience Engineer / General Engineer / Emergency Support Specialist Company: None Start At: None Ends At: None Location: None Description: None | W39: School: The George Washington University Degree: MS, Engineering Management program with a focus in Crisis, Emergency, and Risk Management Activities: None School: University of Maryland Degree: Bachelor of Science, Mechanical Engineering Activities: None | X39: Fellow of the Business Continuity Institute (FBCI) with ~15 years leading operational resilience, crisis management, and risk programmes across life sciences, financial market regulation, and U.S. critical energy infrastructure. Equally passionate about building the AI-powered tools that make resilience faster, smarter, and more accessible. I have conceived and deployed multiple AI applications using multi-agent LLM architectures and vibe-coding platforms (Claude Cowork, Google AI Studio, Mistral Vibe CLI): Resilience Architect, an exercise generation platform orchestrating Gemini, Mistral (adversarial red-team critique), and Claude in a cross-model verified RAG pipeline with a custom Mistral API agent for real-world news monitoring; Crisis Compass, a crisis coordination platform with Gemini-powered plan parsing and Mistral pre-mortem stress testing; and ReguCheck, a DORA/EBA regulatory compliance tool with AI-powered scoring and ACPR audit simulation. I also deployed a Microsoft Copilot Studio crisis agent globally at AstraZeneca and built PowerApps that achieved >90% adoption on first deployment. Currently leading the global BCM and crisis management programme for AstraZeneca Oncology R&D—an ISO 22301-aligned framework spanning laboratories, clinical manufacturing, and vivariums across North America, Europe, and Asia. Recognised as an AI leader across Oncology R&D and the wider AstraZeneca resilience network; frequently engaged as an SME on AI capabilities and collaborating with IT to develop secure in-house AI-powered applications. Previously modernised FINRA’s enterprise BCM and crisis-response framework. Earlier, spent a decade at the U.S. DOT (PHMSA) coordinating federal crisis response during national-scale incidents including Colonial Pipeline, Merrimack Valley, Hurricane Maria, and Aliso Canyon. Contributed to legislation with digital resilience provisions similar to DORA. Built one of PHMSA’s earliest workflow automation tools—a SharePoint system for 49 CFR Part 194 oil spill response plan reviews used for 99% of reviews over five years. I lead the BCI Operational Resilience SIG and serve on the BCI AI SIG leadership committee. Presented at BCI World 2024 on cross-sector exercising and moderated a panel on psychological resilience in crisis teams. Dual citizen of France and the United States. Open to connecting with resilience, risk, AI, and crisis management professionals. | Y39: 🇫🇷🇺🇸 Franco-American | FBCI | Resilience & AI Leader | Multi-Agent LLM App Builder | Crisis Management & BCM | BCI OpRes SIG Leader | Pharma · Financial Regulation · Infrastructure | Z39: Nathan_Schoenkin,_FBCI.png
A40: Gene eubanks | C40: https://www.linkedin.com/in/gene-eubanks-2719ab331 | D40: 0 | F40: Executive Director | G40: Zapata AI | N40: United States | O40: Reading, Pennsylvania | W40: Title: Executive Director Company: None Start At: None Ends At: None Location: None Description: None | Z40: Executive Director at Zapata.ai | AA40: Gene_eubanks.png
A41: Eric Yao | B41: Eric Yao.png | C41: https://www.linkedin.com/in/yaohaohui | D41: 2327 | F41: Director of Business Development | G41: XtalPi | H41: Biotechnology Research | I41: http://en.xtalpi.com | J41: https://www.linkedin.com/company/xtalpi/ | L41: 501-1000 | M41: 9 mos | N41: United States | O41: Cambridge, Massachusetts | Q41: Title: General's story Source: jiangsu wenyi publisher Summary: None URL: https://www.cnki.com.cn/Article/CJFDTotal-GZSZ2013Z2035.htm | T41: Title: Volunteer Start At: 01/2018 Ends At: 04/2018 Company: University of Iowa Health Care Cause: Health Description: None | U41: Name: Hunting and Fishing Guide Authority: Iowa Department of Natural Resources Date: 2018-1 URL: https://linkedin.com/company/1068225 Name: Associate Member Authority: National Rifle Association Date: 2018-3 URL: https://linkedin.com/company/12756 | W41: Title: Director of Business Development Company: None Start At: None Ends At: None Location: None Description: None Title: Founder Company: None Start At: None Ends At: None Location: None Description: None Title: Associate Director of BD Company: None Start At: None Ends At: None Location: None Description: None Title: Associate Director Business Development Company: None Start At: None Ends At: None Location: None Description: None Title: Founder Company: None Start At: None Ends At: None Location: None Description: None Title: Business Development Representative Company: None Start At: None Ends At: None Location: None Description: None Title: Marketing Specialist Company: None Start At: None Ends At: None Location: None Description: None Title: Student Security Officer Company: None Start At: None Ends At: None Location: None Description: None Title: Teaching Assistant Company: None Start At: None Ends At: None Location: None Description: None | X41: School: University of Iowa Degree: Bachelor's degree, Marketing/Marketing Management, General Activities: None | Y41: Experienced international Business Development director with a demonstrated history of working in the medical service and pharmaceutical industry focusing primarily on managing existing relationships and generating new business leads. Professionally skilled in arranging multi-language international meetings, business negotiations, and directing new sales initiatives. | Z41: AI enables better cures | AA41: Eric_Yao.png

Sheet Quantum Bio & Medicine investor
A1: name | B1: logo | C1: Invested in | D1: description | E1: short_description | F1: website | G1: contact_email | H1: founded_on | I1: twitter | J1: facebook | K1: linkedin | L1: locations | M1: city | N1: region | O1: country | P1: num_investments_funding_rounds | Q1: num_exits | R1: founders | S1: num_employees_enum | T1: ipo_status
A2: European Investment Bank | B2: European Investment Bank.png | C2: Algorithmiq | D2: The European Investment Bank offers lending, borrowing, and treasury services primarily within the European Union. It provides project loans for public and private sectors, loans to banks and intermediaries, structured finance products, guarantees, and securitization instruments for debts. Additionally, EIB offers equity and fund investment products, including infrastructure and environmental funds, as well as venture capital funds. EIB also supports microfinance and risk-sharing finance for research and innovation and provides technical expertise for sustainable energy projects. Its services include infrastructure advisory, urban development support, guarantees for transport infrastructure, and funding for public-private partnerships and small- to medium-sized enterprises. The bank serves various sectors, including transportation, energy, health, education, and agriculture. | E2: European Investment Bank is a financial entity that offers services related to lending, borrowing, and treasury management. | F2: https://www.eib.org | G2: Infodesk@eib.org | H2: 21186 | I2: https://x.com/EIB | J2: http://www.facebook.com/EuropeanInvestmentBank | K2: http://www.linkedin.com/company/european-investment-bank | L2: Luxembourg,Luxembourg,Luxembourg,Europe | M2: Luxembourg | N2: Luxembourg | O2: Luxembourg | P2: 513 | Q2: 167 | S2: 1001-5000 | T2: private
A3: Andreessen Horowitz | B3: Andreessen Horowitz.png | C3: Rigetti Computing | D3: Andreessen Horowitz is a venture capital firm specializing in investing in seed, start-ups, early, mid-stage, growth, and late-stage. It prefers to invest in the social media business and technology sector with a focus on software, back-end infrastructure, the infrastructure of the Internet, cloud computing, enterprise software and services, consumer, business Internet, mobile-Internet, consumer Internet, cloud computing, data storage, social network browsers data-storage, consumer electronics, networking functions, software related biology, biotech, and medicine companies at the intersection of computer science and life sciences with a focus on digital therapeutics, cloud technology in biology, and computational medicine. | E3: Andreessen Horowitz is a stage-agnostic venture capital firm with assets under management across multiple funds. | F3: http://www.a16z.com | G3: menlopark-info@a16z.com | H3: 39819 | I3: https://x.com/a16z | J3: https://www.facebook.com/andreessenhorowitz | K3: https://www.linkedin.com/company/a16z | L3: Menlo Park,California,United States,North America | M3: Menlo Park | N3: California | O3: United States | P3: 1910 | Q3: 292 | R3: Ben Horowitz,Marc Andreessen | S3: 251-500 | T3: private
A4: NVIDIA | B4: NVIDIA.png | C4: SandboxAQ | D4: NVIDIA is a computing platform company innovating at the intersection of graphics, HPC and AI. The company specialises in the manufacture of graphics processor technologies for workstations, desktop computers, and mobile devices. The company is a major supplier of integrated circuits used for personal computer motherboard chipsets, graphics processing units (GPUs), and game consoles. | E4: NVIDIA is a computing platform company operating at the intersection of graphics, HPC, and AI. | F4: https://www.nvidia.com | G4: info@nvidia.com | H4: 34093 | I4: https://x.com/nvidia | J4: https://www.facebook.com/NVIDIA.AP | K4: https://www.linkedin.com/company/nvidia | L4: Santa Clara,California,United States,North America | M4: Santa Clara | N4: California | O4: United States | P4: 186 | Q4: 20 | R4: Chris Malachowsky,Curtis Priem,Jensen Huang | S4: 10001+ | T4: public
A5: Bpifrance | B5: Bpifrance.png | C5: Pasqal | D5: Bpifrance provides financial solutions for companies that are booting up the listing on the stock exchange and credit equity. It includes OSEO, CDC Entreprises, FSI, and FSI Regions to offer in your area of financial solutions at every stage of the life of your business. | E5: Bpifrance provides financial solutions for companies that are booting up the listing on the stock exchange and credit equity. | F5: https://www.bpifrance.com | G5: F3A@bpifrance.fr | H5: 12/31/2012 | I5: https://x.com/Bpifrance | J5: https://www.facebook.com/bpifrance | K5: https://www.linkedin.com/company/bpifrance | L5: Maisons-alfort,Ile-de-France,France,Europe | M5: Maisons-alfort | N5: Ile-de-France | O5: France | P5: 1624 | Q5: 197 | S5: 1001-5000 | T5: private
A6: Franklin Templeton | B6: Franklin Templeton.png | C6: Rigetti Computing | D6: Franklin Templeton is an investment management firm offering mutual funds, ETFs, and wealth management services. The firm provides investment solutions across asset classes, including equity, fixed income, and alternative investments. Through subsidiaries such as Fiduciary Trust Company International and Clarion Partners, Franklin Templeton serves individual and institutional clients globally. | E6: Franklin Templeton is a investment firm that offers mutual funds for individuals and institutions. | F6: http://www.franklintempleton.com | H6: 17168 | I6: https://x.com/FTI_US | J6: http://www.facebook.com/franklintempleton | K6: https://www.linkedin.com/company/franklin-templeton | L6: San Mateo,California,United States,North America | M6: San Mateo | N6: California | O6: United States | P6: 235 | Q6: 76 | R6: Rupert H. Johnson,Rupert H. Johnson, Sr. | S6: 5001-10000 | T6: private
A7: HSG | B7: HSG.png | C7: XtalPi | D7: HSG, formerly known as Sequoia Capital China, is a leading venture capital and private equity firm investing globally in the technology, healthcare, and consumer sectors. With offices in Hong Kong, Shanghai, Beijing, Shenzhen, London, Tokyo, and Singapore. HSG manages over 55 billion USD in assets across various funds for top institutional investors. Founded in 2005, HSG has nurtured entrepreneurship and innovation, backing more than 1,500 companies with transformative technologies, disruptive business models, and high-growth potential. To date, more than 160 HSG portfolio companies have listed on public stock exchanges, while over 140 private portfolio companies have reached unicorn status. Throughout the past two decades, HSG has evolved into a fully integrated investment platform spanning seed, venture, growth, buyout, and infrastructure investing, as well as public equities investment. HSG is committed to helping founders and companies build legendary companies that endure while consistently generating superior returns for our limited partners. By partnering with HSG, companies benefit from HSG’s extensive resources, including a robust entrepreneurial community and industry expertise. | E7: HSG is a venture capital and private equity firm investing globally in the technology, healthcare, and consumer sectors. | F7: https://www.hsgcap.com | G7: info@hsgcap.com | H7: 38361 | K7: https://www.linkedin.com/company/hong-shan | L7: Hong Kong,Hong Kong Island,Hong Kong,Asia | M7: Hong Kong | N7: Hong Kong Island | O7: Hong Kong | P7: 1187 | Q7: 129 | R7: Neil Shen | S7: 251-500 | T7: private
A8: Alumni Ventures | B8: Alumni Ventures.png | C8: Menten AI, Rigetti Computing | D8: Alumni Ventures is a venture capital firm that offers accredited investors access to diversified venture portfolios. The firm operates multiple funds, including alumni-focused and thematic funds, and co-invests alongside established venture firms. Investors can choose between fund-based investing or selecting individual deals. Alumni Ventures leverages a broad network to source capital, evaluate opportunities, and support portfolio companies. The firm manages a portfolio encompassing over 1,400 venture-backed companies across various sectors and stages. | E8: Alumni Ventures Group is an venture capital investment firm that manages fund families that invest in a portfolio of companies. | F8: http://www.av.vc | G8: info@av.vc | H8: 41640 | I8: https://x.com/alumniventures | J8: https://www.facebook.com/alumniventures | K8: https://www.linkedin.com/company/alumniventures | L8: Manchester,New Hampshire,United States,North America | M8: Manchester | N8: New Hampshire | O8: United States | P8: 2269 | Q8: 229 | R8: Luke Antal,Michael Collins,Michael Madden | S8: 101-250 | T8: private
A9: Bessemer Venture Partners | B9: Bessemer Venture Partners.png | C9: Rigetti Computing | D9: Bessemer Venture Partners is a venture capital firm that invests in early-stage and growth-stage companies across technology, healthcare, and consumer sectors. It provides capital to startups and emerging businesses while supporting founders with strategic guidance, operational insight, and network access. The firm participates in multiple funding stages, from seed investments to later growth rounds, and works closely with portfolio companies on product development, market expansion, and organizational scaling. Its investment activities span software, cloud infrastructure, fintech, biotech, and internet-enabled businesses, aligning capital deployment with long-term company building. | E9: Bessemer Venture Partners is a venture capital firm that invests in enterprise, consumer, and healthcare early-to-late stage startups. | F9: http://www.bvp.com | G9: businessplans@bvp.com | H9: 4019 | I9: https://x.com/bessemervp | J9: https://www.facebook.com/bessemer | K9: https://www.linkedin.com/company/bessemer-venture-partners | L9: San Francisco,California,United States,North America | M9: San Francisco | N9: California | O9: United States | P9: 1572 | Q9: 331 | R9: Henry Phipps | S9: Nov-50 | T9: private
A10: Felicis | B10: Felicis.png | C10: Rigetti Computing | D10: Felicis is a venture capital firm that focuses on backing founders who are building iconic companies capable of transcending boundaries. The firm invests directly in their growth, supporting innovative ideas across various sectors, including AI, health, and security. | E10: Felicis invests in seed through Series C stage companies across multiple sectors, industries, and frontier tech. | F10: http://www.felicis.com | G10: hello@felicis.com | H10: 38727 | I10: https://x.com/felicis | J10: https://www.facebook.com/FelicisVentures | K10: http://www.linkedin.com/company/felicis-ventures | L10: Menlo Park,California,United States,North America | M10: Menlo Park | N10: California | O10: United States | P10: 736 | Q10: 176 | R10: Aydin Senkut | S10: Nov-50 | T10: private
A11: Daphni | B11: Daphni.png | C11: Pasqal | D11: Founded in 2015, daphni is a venture capital firm that invests primarily from seed to Series A in projects with a positive societal and/or environmental impact. With almost €1 billion under management, daphni has over 90 active portfolio companies, including Back Market, Pasqal, Carbon Maps, Hubcycle, Swile, Epyr, Ankar, Moonwatt, and Karavela. The funds managed by daphni focus on new usages and disruptive deeptech technologies, especially ones with a strong science angle in biology, chemistry, physics, mathematics, and life sciences. As a mission-driven and B Corp certified company, daphni is committed to shaping a more sustainable future. In order to do so, daphni is powered by a community of 450+ entrepreneurs, executives, academics, creatives, and experts who engage with both daphni’s team and the founders backed in its portfolio. Flamel, daphni’s proprietary open-innovation platform, incorporates AI-driven components that strengthen every step of our mission. This is venture capital, done our way. Since 2022, daphni has managed Dastore, a fund launched in partnership with Carrefour, dedicated to support early stage startups building the future of commerce. At the end of 2024, daphni announced its work on Time4, a seed fund designed to support projects led by entrepreneurs from unique backgrounds and untapped markets. | E11: daphni is a VC firm that invests primarily from seed to Series A in projects with a positive societal and/or environmental impact. | F11: http://www.daphni.com | H11: 42008 | I11: https://x.com/daphnivc | J11: https://www.facebook.com/daphnivc/ | K11: https://www.linkedin.com/company/daphni/ | L11: Paris,Ile-de-France,France,Europe | M11: Paris | N11: Ile-de-France | O11: France | P11: 121 | Q11: 8 | R11: Marie Ekeland,Mathieu Daix,Pierre-Eric Leibovici,Pierre-Yves Meerschman,Willy Braun | S11: Nov-50 | T11: private
A12: Khosla Ventures | B12: Khosla Ventures.png | C12: Menten AI | D12: Khosla Ventures is a venture capital firm that invests in early- to late-stage companies across sectors like AI, healthcare, sustainability, and consumer technology. It manages multiple funds, focusing on startups with innovative technologies or business models. The firm primarily targets sectors like AI, climate tech, digital health, and medtech, offering strategic support to help build long-lasting companies. | E12: Khosla Ventures provides venture assistance to entrepreneurs in AI, sustainability, enterprise, consumer, health and frontier technologies. | F12: http://www.khoslaventures.com | G12: kv@khoslaventures.com | H12: 37987 | I12: https://x.com/khoslaventures | J12: https://www.facebook.com/KhoslaVentures | K12: https://www.linkedin.com/company/khosla-ventures | L12: Menlo Park,California,United States,North America | M12: Menlo Park | N12: California | O12: United States | P12: 1422 | Q12: 198 | R12: Samir Kaul,Vinod Khosla | S12: 101-250 | T12: private
A13: Y Combinator | B13: Y Combinator.png | C13: Menten AI | D13: Y Combinator is a startup accelerator that provides funding and mentorship to early-stage companies. It offers a program where startups receive guidance from experienced entrepreneurs and investors. The organization helps founders in their business models and develop their products. Y Combinator serves industries such as technology, healthcare, and finance. | E13: Y Combinator is a startup accelerator that invests in a wide range of startups. | F13: http://www.ycombinator.com | G13: info@ycombinator.com | H13: 38355 | I13: http://www.x.com/ycombinator | J13: http://www.facebook.com/YCombinator | K13: https://www.linkedin.com/school/y-combinator | L13: Mountain View,California,United States,North America | M13: Mountain View | N13: California | O13: United States | P13: 8137 | Q13: 729 | R13: Armand Cognetta,Jessica Livingston,Paul Graham,Robert Morris,Trevor Blackwell | S13: 51-100 | T13: private
A14: QED Investors | B14: QED Investors.png | C14: Quantinuum | D14: QED Investors is an investment firm that supports high-growth companies and businesses. The firm typically provides a combination of both capital and capability. But common to all the firm's partnerships is a shared conviction that information plays a decisive role in the success of the company, a mutual desire for a high degree of direct engagement, and a shared enthusiasm for experimentation and learning. | E14: QED Investors is an investment firm that supports high-growth companies and businesses. | F14: http://www.qedinvestors.com | H14: 39083 | I14: https://x.com/QEDInvestors | J14: http://www.facebook.com/QEDInvestors | K14: http://www.linkedin.com/company/qed-investors | L14: Alexandria,Virginia,United States,North America | M14: Alexandria | N14: Virginia | O14: United States | P14: 391 | Q14: 47 | R14: Caribou Honig,Frank Rotman,Nigel Morris | S14: Nov-50 | T14: private
A15: New Enterprise Associates | B15: New Enterprise Associates.png | C15: IonQ | D15: New Enterprise Associates is a venture capital firm that invests in technology and healthcare startups. The firm engages with entrepreneurs at various stages of business development, providing support from initial funding to public offerings. The company focuses on the technology and healthcare industries. | E15: New Enterprise Associates is a venture capital firm that focuses on investments in technology and healthcare startups. | F15: http://www.nea.com | G15: bd@nea.com | H15: 28126 | I15: https://www.x.com/NEA | J15: https://www.facebook.com/NEAvc | K15: https://www.linkedin.com/company/new-enterprise-associates | L15: Menlo Park,California,United States,North America | M15: Menlo Park | N15: California | O15: United States | P15: 2407 | Q15: 660 | R15: Chuck Newhall,Frank A. Bonsal,Richard Kramlich | S15: 101-250 | T15: private
A16: S32 | B16: S32.png | C16: SandboxAQ | D16: S32 the new venture fund launched by Bill Maris, was named in homage to Section 31, an intelligence agency from the Star Trek universe. Maris, the GV (Google Ventures) founder/former-CEO, has raised $150 million for the project that will focus on various investments. The fund will be run directly by Maris and primarily based out of San Diego. | E16: S32 is a venture capital fund that invests at the cutting edge of technology, healthcare, and life sciences. | F16: https://s32.com/ | G16: press@section32.com | H16: 42740 | I16: https://x.com/section32vc | K16: https://www.linkedin.com/company/section-32 | L16: San Diego,California,United States,North America | M16: San Diego | N16: California | O16: United States | P16: 148 | Q16: 26 | S16: Nov-50 | T16: private
A17: Bosch Ventures | B17: Bosch Ventures.png | C17: IonQ | D17: Bosch Ventures (Robert Bosch Venture Capital GmbH) is the corporate venture capital company of the Bosch Group, a leading global supplier of technology and services. Bosch Ventures invests worldwide in innovative start-up companies at all stages of their development. Its investment activities focus on technology companies working in areas of business of current and future relevance for Bosch, above all, automation and electrification, energy efficiency, enabling technologies, and healthcare systems. Bosch Ventures also invests in services and business models as well as new materials that are relevant to the above-mentioned areas of business. Bosch Ventures invests from EUR 500k for a seed funding to more than EUR 15m per company for usually 10% to 25% equity position. Bosch Ventures prefers to syndicate their investments with existing or new investors in the company and can take the lead as necessary. | E17: Bosch Ventures (Robert Bosch Venture Capital GmbH) is the corporate venture capital company of the Bosch Group | F17: http://www.rbvc.com | G17: Info.RBVC@de.bosch.com | H17: 39083 | K17: https://www.linkedin.com/company/robert-bosch-venture-capital/ | L17: Stuttgart,Baden-Wurttemberg,Germany,Europe | M17: Stuttgart | N17: Baden-Wurttemberg | O17: Germany | P17: 156 | Q17: 30 | R17: Adam Jackson | S17: Nov-50 | T17: private
A18: XAnge | B18: XAnge.png | C18: Qubit Pharmaceuticals | D18: XAnge is a BCorp-certified early-stage investment fund managing €700 million, with offices in Paris, Berlin, and Brussels. The fund backs European founders who aim to transform daily life through technology, investing between €500,000 and €10 million from the seed stage onwards. XAnge’s investment focus spans deeptech, health, fintech, SaaS, and e-commerce, with a portfolio including Lydia, Welcome to the Jungle, Believe, MrSpex, and Ledger. XAnge is the innovation-driven venture capital brand of the Siparex Group. | E18: European Early-Stage Venture Capital Firm | F18: https://www.xange.vc | G18: contact@xange.fr | H18: 37622 | I18: https://x.com/xangevc | J18: https://www.facebook.com/XAngeVC/ | K18: http://www.linkedin.com/company/xange-private-equity | L18: Paris,Ile-de-France,France,Europe | M18: Paris | N18: Ile-de-France | O18: France | P18: 276 | Q18: 59 | S18: Nov-50 | T18: private
A19: Uncork Capital | B19: Uncork Capital.png | C19: Menten AI | D19: Uncork Capital is a San Francisco-based venture capital firm that helps founders build category-defining companies from the earliest stages. For more than two decades, through multiple boom-and-bust cycles and across the tech landscape, the firm has backed over 275 companies, including Fitbit (NYSE: FIT, Google), Sendgrid (NYSE: SEND, Twilio), Eventbrite (NYSE: EB), Poshmark (NASD: POSH), and Postmates (UBER), as well as fast-growing startups like Human Interest, LaunchDarkly, Carrot Fertility, Tailscale, Loft Orbital, Hallow, Wrapbook, Crossbeam, Fountain, GPTZero, Nuon, Ivo, Numeral, and Final Round. Today, Uncork continues to support the next generation of builders shaping industries across AI, SaaS, infrastructure, consumer, and frontier tech. | E19: Uncork Capital is one of Silicon Valley’s most enduring seed firms — and a founder’s most trusted guide. | F19: http://www.uncorkcapital.com | G19: contact@uncorkcapital.com | H19: 38022 | I19: https://x.com/uncorkcap | J19: https://www.facebook.com/uncorkcapital/ | K19: https://www.linkedin.com/company/uncorkcapital | L19: San Francisco,California,United States,North America | M19: San Francisco | N19: California | O19: United States | P19: 463 | Q19: 116 | R19: Jeff Clavier | S19: Nov-50 | T19: private
A20: K5 Global | B20: K5 Global.png | C20: Algorithmiq | D20: K5 Global Advisor LLC (“K5”) is a venture capital firm and incubation studio that supports founders across the business lifecycle. The firm was founded in 2018 by Michael Kives and Bryan Baum and has deployed capital of around $1B as of March 31, 2024. K5 invests across multiple stages, from seed through growth stage companies, with a focus on Enterprise SaaS, Vertical SaaS, and FinTech. In 2023, Keenan Rice and Daniel Marcotte, investors from Tokyo Black Capital Advisors, LLC, and both on the founding team of Looker (acquired by Google in 2020 for $2.6B), joined with K5’s early-stage SaaS investing team. K5 seeks to help innovative companies expand their networks and best position them to achieve growth targets. | E20: K5 Global is a venture capital firm and incubation studio that offers investment from inception to IPO. | F20: http://www.k5global.com/ | G20: inquiries@k5global.com | H20: 43101 | K20: https://www.linkedin.com/company/k5global/ | L20: San Francisco,California,United States,North America | M20: San Francisco | N20: California | O20: United States | P20: 218 | Q20: 24 | R20: Bryan Baum,Michael Kives | S20: Nov-50 | T20: private
A21: Lockheed Martin Ventures | B21: Lockheed Martin Ventures.png | C21: IonQ | D21: Lockheed Martin Ventures is the venture arm of Lockheed Martin Corporation. The mission of Lockheed Martin Ventures is to make strategic investments in companies that are developing disruptive, cutting-edge technologies in core businesses and new markets important to Lockheed Martin. These emerging innovations have the potential to become foundational technologies that solve the complex challenges customers face. | E21: Lockheed Martin Ventures is the venture arm of Lockheed Martin Corporation. | F21: http://www.lockheedmartin.com/us/who-we-are/lockheed-martin-ventures.html | G21: lm.ventures@lmco.com | H21: 39083 | K21: https://www.linkedin.com/company/lockheed-martin | L21: Bethesda,Maryland,United States,North America | M21: Bethesda | N21: Maryland | O21: United States | P21: 106 | Q21: 10 | S21: Nov-50 | T21: private
A22: US Innovative Technology Fund | B22: US Innovative Technology Fund.png | C22: SandboxAQ | D22: US Innovative Technology Fund is an investment firm that supports early- and growth-stage technology companies developing commercial and defense applications. The firm focuses on sectors such as defense technology, artificial intelligence, logistics, space, biotech, and next-generation computing. | E22: US Innovative Technology Fund is an investment firm that supports early- and growth-stage technology companies. | F22: https://usitfund.com | G22: info@usitfund.com | H22: 44562 | K22: https://www.linkedin.com/company/us-innovative-technology-fund | L22: Pittsburgh,Pennsylvania,United States,North America | M22: Pittsburgh | N22: Pennsylvania | O22: United States | P22: 30 | Q22: 2 | R22: Thomas Tull | S22: 46032 | T22: private
A23: BNP Paribas | B23: BNP Paribas.png | C23: SandboxAQ | D23: BNP Paribas provides banking, financing, investment, savings, and protection solutions. The Group's three operational divisions are mobilized to support each type of clientele in their growth and development projects including corporate and institutional banking, commercial, personal banking, investment and protection services. The company provide financing and investment services to retail customers, associations, businesses, and corporations. | E23: BNP Paribas is a financial service company that offers commercial, banking, and investment services. | F23: https://group.bnpparibas | G23: enquiries@au.bnpparibas.com | H23: 9/23/1966 | I23: https://x.com/BNPParibas | J23: https://www.facebook.com/BNPParibasGroup/ | K23: https://www.linkedin.com/company/bnp-paribas | L23: Paris,Ile-de-France,France,Europe | M23: Paris | N23: Ile-de-France | O23: France | P23: 265 | Q23: 89 | R23: Zahid Moneer | S23: 10001+ | T23: public
A24: Tiger Global Management | B24: Tiger Global Management.png | C24: Algorithmiq | D24: Tiger Global Management is an investment firm focusing on both public and private equity. It invests in global companies leveraging technological innovation. Its public equity business includes long/short and growth strategies, while its private equity business targets early to late-stage companies across various industries. Tiger Global's approach centers on identifying high-quality growth opportunities, working with portfolio companies across their lifecycle. | E24: Tiger Global Management is an investment firm that invests in global public and private companies. | F24: https://www.tigerglobal.com | G24: media@tigerglobal.com | H24: 36894 | K24: https://www.linkedin.com/company/tiger-global-management | L24: New York,New York,United States,North America | M24: New York | N24: New York | O24: United States | P24: 1244 | Q24: 212 | R24: Chase Coleman | S24: 101-250 | T24: private
A25: OurCrowd | B25: OurCrowd.png | C25: Polaris Quantum Biotech | D25: OurCrowd is a venture investing platform that enables institutions and individuals to invest and engage in emerging companies. OurCrowd was started in 2013, driven by the idea that the business of building startups grows bigger and better when the global 'crowd' gains access to VC-level investment opportunities. | E25: OurCrowd is a venture investing platform that enables institutions and individuals to invest and engage in emerging companies. | F25: http://www.ourcrowd.com | G25: info@ourcrowd.com | H25: 41276 | I25: https://x.com/OurCrowd | J25: http://www.facebook.com/Ourcrowdfund | K25: http://www.linkedin.com/company/ourcrowd-llc | L25: Jerusalem,Yerushalayim,Israel,Asia | M25: Jerusalem | N25: Yerushalayim | O25: Israel | P25: 352 | Q25: 61 | R25: Jonathan Medved,Steve Wishner | S25: 101-250 | T25: private
A26: JP Morgan Chase | B26: JP Morgan Chase.png | C26: Quantinuum | D26: JPMorgan Chase is a financial holding company, provides various financial services worldwide. The company's Investment Bank segment provides investment banking products and services, including advising on corporate strategy and structure, capital raising in equity and debt markets, risk management, market-making in cash securities and derivative instruments, and prime brokerage and research. It was founded in February 2000 and is based in New York, United States. | E26: JP Morgan Chase is a global financial services provider that offers investment banking, asset management, treasury, and other services. | F26: https://www.jpmorganchase.com | G26: jpmc.cpo@jpmchase.com | H26: 36537 | I26: https://x.com/jpmorgan | J26: https://www.facebook.com/jpmorganchase | K26: https://www.linkedin.com/company/jpmorganchase/ | L26: New York,New York,United States,North America | M26: New York | N26: New York | O26: United States | P26: 367 | Q26: 137 | R26: John Pierpont Morgan,John Thompson | S26: 10001+ | T26: public
A27: Shunwei Capital | B27: Shunwei Capital.png | C27: XtalPi | D27: Shunwei Capital is a venture capital fund that focuses on early to mid-stage investments in local internet industry. It specializes in incubation, startups, early to mid-stage, and growth capital investments. It seeks to invest in the technology, media, telecommunications, high technology, new media, games, internet finance, and rural area internet sectors. Their investors include sovereign wealth funds, fund of funds, university endowment funds, and family offices. | E27: Shunwei Capital is a venture capital fund focused primarily on early- to mid-stage investments in China's internet industry. | F27: http://shunwei.com | G27: deals@shunwei.com | H27: 40544 | I27: https://x.com/shunweicapital | J27: https://www.facebook.com/shunweicapital/ | K27: https://www.linkedin.com/company/%E9%A1%BA%E4%B8%BA%E8%B5%84%E6%9C%AC/ | L27: Beijing,Beijing,China,Asia | M27: Beijing | N27: Beijing | O27: China | P27: 563 | Q27: 41 | R27: Jun Lei,Tuck Lye Koh | S27: Nov-50 | T27: private
A28: Inventure | B28: Inventure.png | C28: Algorithmiq | D28: We commit to early-stage founders with roots in the Nordics and Baltics. Those we back are in. We believe in them fully, fight for them fiercely, and build lasting trust that goes both ways. We back the few—because they’re the ones who can build futures others can’t imagine and improve life for the many. | E28: We commit to early-stage founders in the Nordics and Baltics. Those we back are in. We believe in them fully, and fight for them fiercely. | F28: https://inventure.vc/ | G28: hello@inventure.vc | H28: 38353 | I28: https://x.com/InventureVC | K28: https://www.linkedin.com/company/inventure/ | L28: Helsinki,Southern Finland,Finland,Europe | M28: Helsinki | N28: Southern Finland | O28: Finland | P28: 165 | Q28: 23 | R28: Kevin Lösch,Sami Lampinen,Timo Tirkkonen | S28: Nov-50 | T28: private
A29: OrbiMed | B29: OrbiMed.png | C29: XtalPi | D29: OrbiMed is a healthcare-dedicated investment firm, with approximately $5 billion in assets under management. OrbiMed's investment advisory business was founded in 1989 with a vision to invest across the spectrum of healthcare companies: from private start-ups to large multinational companies. OrbiMed manages the Caduceus Private Investments series of venture capital funds and a family of public equity investment funds. | E29: OrbiMed is a healthcare-dedicated investment firm focusing on biopharmaceuticals for medical devices and diagnostics. | F29: http://www.orbimed.com | G29: info@orbimed.com | H29: 32509 | I29: https://x.com/OrbiMed | J29: https://www.facebook.com/OrbiMed-Advisors-522321737819113 | K29: https://www.linkedin.com/company/orbimed-advisors | L29: New York,New York,United States,North America | M29: New York | N29: New York | O29: United States | P29: 765 | Q29: 290 | R29: Michael B. Sheffery,Sam Isaly,Sven Borho | S29: 101-250 | T29: private
A30: Paladin Capital Group | B30: Paladin Capital Group.png | C30: SandboxAQ | D30: Paladin Capital Group is a leading global investor that supports and grows the world’s most innovative companies through venture investment, expansion, and growth capital. Paladin is a leader in investing in technologies, products, and services focused on dual use in both commercial and governmental markets with a strong value-add culture. The Paladin team merges financial expertise with national security and technical competence to add value across a wide array of market sectors and company stages. Paladin is focused on being an active investor—bringing decades of experience, advice, access, and relationships to its portfolio companies. Their most recent fund focuses on digital infrastructure resilience, investing globally in advanced technologies and solutions which enable, monitor, manage, and defend critical infrastructure that is dependent on cyber space. The firm is headquartered in Washington, DC, with offices in New York City, Silicon Valley, London, and Luxembourg. | E30: Paladin is a global investor that supports innovative technology companies through venture investment and growth capital. | F30: http://www.paladincapgroup.com | G30: submissions@paladincapgroup.com | H30: 36892 | I30: https://x.com/paladincap | K30: http://www.linkedin.com/company/64897 | L30: Washington,District of Columbia,United States,North America | M30: Washington | N30: District of Columbia | O30: United States | P30: 192 | Q30: 55 | R30: Mark Maloney,Michael R. Steed | S30: Nov-50 | T30: private
A31: Alphabet | B31: Alphabet.png | C31: XtalPi | D31: Alphabet is a holding company that provides projects with resources, freedom, and focus to make their ideas happen. Alphabet is the holding company for Google and several Google entities, including Google X, Google Ventures, Google Capital, Calico, and its Life Sciences efforts. The company's CEO, Larry Page announced the operational restructuring effort for Alphabet Inc. to replace Google Inc. as the official publicly-traded entity. He announced that all shares of Google would automatically convert into the same number of shares of Alphabet, with all of the same rights. The two classes of shares will continue to trade on Nasdaq as GOOGL and GOOG. | E31: Alphabet is a holding company that provides projects with resources, freedom, and focus to make their ideas happen. | F31: https://abc.xyz | H31: 42045 | I31: https://x.com/alphabetlnc | J31: https://www.facebook.com/alphabetxyz | K31: https://www.linkedin.com/company/alphabet-inc | L31: Mountain View,California,United States,North America | M31: Mountain View | N31: California | O31: United States | P31: 31 | Q31: 3 | R31: Larry Page,Sergey Brin | S31: 10001+ | T31: public
A32: European Innovation Council | B32: European Innovation Council.png | C32: Pasqal, Qnami, Qubit Pharmaceuticals | D32: The European Innovation Council aims to support top-class innovators, entrepreneurs, small companies, and researchers with bright ideas. The EIC co-invests alongside private investors in early-stage startups that have ESG impacts. | E32: The European Innovation Council aims to support top-class innovators, entrepreneurs, small companies and researchers with bright ideas. | F32: https://eic.ec.europa.eu | H32: 3/25/1957 | I32: https://x.com/EUeic | J32: https://www.facebook.com/EIC-The-European-Innovation-Council-2462855093727279 | K32: https://www.linkedin.com/company/eismea | L32: Brussels,Brussels Hoofdstedelijk Gewest,Belgium,Europe | M32: Brussels | N32: Brussels Hoofdstedelijk Gewest | O32: Belgium | P32: 1236 | Q32: 38 | S32: 501-1000 | T32: private
A33: Amgen | B33: Amgen.png | C33: Quantinuum | D33: Amgen is a biotechnology company that develops and manufactures human therapeutics for various illnesses and diseases. The company is values-based and deeply rooted in science and innovation to transform new ideas and discoveries into medicines for patients with serious diseases. They offer products for treating illness in the areas of oncology/hematology, cardiovascular, inflammation, bone health, nephrology, and neuroscience. | E33: Amgen is a biotechnology company that develops and manufactures human therapeutics for various illnesses and diseases. | F33: http://www.amgen.com | G33: amgenmediarelations@amgen.com | H33: 29221 | I33: https://x.com/amgen | J33: https://www.facebook.com/amgenbiotech | K33: https://www.linkedin.com/company/amgen | L33: Thousand Oaks,California,United States,North America | M33: Thousand Oaks | N33: California | O33: United States | P33: 19 | Q33: 10 | R33: George Rathmann | S33: 10001+ | T33: public
A34: Omnes Capital | B34: Omnes Capital.png | C34: Qubit Pharmaceuticals | D34: Omnes VC is the Venture Capital arm of Omnes Capital, a leading private equity firm dedicated to energy transition and innovation with €4.8 billion in assets under management and a 20 year + experience in: venture capital, buyout & growth capital, private debt, renewable energy, co-investment, secondary funds of funds. Omnes Capital is fully independent. With 65 business sales including 14 IPOs carried out in 16 years, Omnes VC is one of the key players in France in financing innovative SMEs with expertise in both Technology and Healthcare sectors. Omnes VC has supported 120 companies and has invested more than €500M in businesses such as Scality, Novaled, BioVex, arGEN-X, Pixium, Blablacar. | E34: Omnes is a leading private equity firm dedicated to energy transition (infrastructure) and innovation (deeptech venture capital). | F34: https://www.omnescapital.com/en/ | G34: contact@omnescapital.com | H34: 36161 | I34: https://x.com/Omnes_VC | J34: http://www.facebook.com/OmnesCapital | K34: http://www.linkedin.com/company/omnes-capital | L34: Paris,Ile-de-France,France,Europe | M34: Paris | N34: Ile-de-France | O34: France | P34: 262 | Q34: 95 | S34: 51-100 | T34: private
A35: NVentures | B35: NVentures.png | C35: Quantinuum | D35: NVentures is a venture capital firm that invests in early-stage and growth-stage technology companies focused on artificial intelligence, computing, and related software and systems. The company evaluates startup opportunities and provides capital and strategic support to help portfolio companies develop products and technologies aligned with high-performance computing and AI platforms. NVentures works with founders and management teams to support innovation across sectors such as AI, robotics, software, and life sciences. The firm also engages in diligence and partnership activities to inform investment decisions and build long-term relationships with emerging technology companies. | E35: NVentures invests in technology companies focused on artificial intelligence and computing. | F35: https://www.nventures.ai | H35: 44197 | L35: Santa Clara,California,United States,North America | M35: Santa Clara | N35: California | O35: United States | P35: 85 | Q35: 2 | S35: 46032 | T35: private
A36: Korea Investment Partners | B36: Korea Investment Partners.png | C36: Quantinuum | D36: Korea Investment Partners (KIP) is a leading venture capital & private equity firm that has over 30 years of experience in providing venture capital to bold and innovative entrepreneurs who want to change the world. Korea Investment Partners invests in leading pioneers like Kakao(KOSDAQ:035720), Naver(KRX:035420), YG Entertainment(KOSDAQ:122870), Bodyfriend, Osstem Implant(KOSDAQ:048260), Doubleu Games(KOSDAQ:192080) and Didi Chuxing. KIP manages over 20 venture and private equity funds with US$1.8 billion in total assets under management. The company operates globally from its Seoul headquarters office with other locations in Shanghai, Beijing, and Sunnyvale. | E36: Korea Investment Partners is a leading venture capital & private equity firm based in Seoul, Shanghai, Beijing, and Sunnyvale. | F36: http://kipvc.com | H36: 31413 | K36: https://www.linkedin.com/company/korea-investment-partners | L36: Seoul,Seoul-t'ukpyolsi,South Korea,Asia | M36: Seoul | N36: Seoul-t'ukpyolsi | O36: South Korea | P36: 483 | Q36: 60 | S36: 51-100 | T36: private
A37: Creative Destruction Lab (CDL) | B37: Creative Destruction Lab (CDL).png | C37: Menten AI | D37: Creative Destruction Lab (CDL) is a no-fee/no-equity organization that delivers an objectives-based mentoring program for massively scalable, pre-seed stage, science- and technology-based companies. Its nine-month program allows founders to learn from experienced entrepreneurs, increasing their likelihood of success. Founded in 2012 by Professor Ajay Agrawal at the University of Toronto’s Rotman School of Management, the program has expanded to thirteen sites across seven countries: Seattle, Oxford, Paris, Atlanta, Estonia, Wisconsin, Vancouver, Calgary, Montreal, Berlin, Melbourne and Halifax. | E37: Creative Destruction Lab (CDL) is a no-fee/no-equity mentoring program for the founders and executives of pre-seed stage ventures. | F37: http://www.creativedestructionlab.com | G37: info@creativedestructionlab.com | H37: 40916 | I37: https://x.com/creativedlab | J37: https://www.facebook.com/creativedestructionlab | K37: https://www.linkedin.com/school/creative-destruction-lab | L37: Toronto,Ontario,Canada,North America | M37: Toronto | N37: Ontario | O37: Canada | P37: 772 | Q37: 83 | R37: Ajay Agrawal,Amaury van Trappen de Buggenoms,Amir Sariri,Anthony Lacavera,Evan Hu,Mustafa Koroglu | S37: 101-250 | T37: private
A38: Tesi | B38: Tesi.png | C38: Algorithmiq | D38: Finnish Industry Investment Ltd is a government-owned investment company. It invests the proceeds accrued from the privatisation of state-owned companies in stimulating the growth and internationalisation of Finnish businesses. Finnish Industry Investment invests in venture capital funds and directly in growth companies, together with private co-investors. The targets are in all sectors. Capital investments are needed for financing the growth of investee companies, and for spin-offs, major industrial investments, and sector and corporate restructurings. The investments of Finnish Industry Investment amount to over MEUR 570 | E38: Tesi is a venture capital and private equity company that accelerates companies’ success stories by investing in them. | F38: https://www.tesi.fi | H38: 34700 | I38: https://x.com/tesifii | K38: https://www.linkedin.com/company/finnish-industry-investment-ltd | L38: Helsinki,Southern Finland,Finland,Europe | M38: Helsinki | N38: Southern Finland | O38: Finland | P38: 138 | Q38: 21 | R38: George Ferguson | S38: Nov-50 | T38: private
A39: OUP (Osage University Partners) | B39: OUP (Osage University Partners).png | C39: IonQ | D39: Osage University Partners is a venture capital firm focused on investing in startups that are commercializing university technologies. Osage partners with research universities to invest in their innovative startups shareing its investment profit with partner institutions. The firm invests in software, hardware, and life science companies at all stages of company development. To date, it has partnered with over 80 universities, including 36 of the top 50 U.S. institutions by research expenditures, and has invested in over 50 of their spinouts. | E39: OUP is a venture capital fund investing in start-ups that commercialize university research. | F39: https://oup.vc/ | G39: info@osagepartners.com | H39: 39814 | I39: https://x.com/OUP_VC | J39: https://www.facebook.com/osageuniversitypartners | K39: https://www.linkedin.com/company/osage-university-partners/ | L39: Bala Cynwyd,Pennsylvania,United States,North America | M39: Bala Cynwyd | N39: Pennsylvania | O39: United States | P39: 231 | Q39: 64 | R39: Marc Singer,Robert Adelson | S39: Nov-50 | T39: private
A40: Infinity Medical | B40: Infinity Medical.png | C40: Polaris Quantum Biotech | E40: Infinity Medical Inc. is a wholesale distributor specializing in Medical-surgical and Dental consumables along with Laboratory equipment | F40: http://infinitymedicalinc.net | G40: info@infinitymedicalinc.net | H40: 37257 | K40: https://www.linkedin.com/company/infinity-medical/ | L40: Calhoun,Georgia,United States,North America | M40: Calhoun | N40: Georgia | O40: United States | P40: 2 | Q40: 1 | S40: 51-100 | T40: private

Sheet Sheet96
A1: Name | B1: LinkedIn | C1: Photo | D1: Followers | E1: Email | F1: Title | G1: Company | H1: Company Industry | I1: Company Website | J1: Company Linkedin | K1: Company Founded In | L1: Company Size | M1: Current Job Duration | N1: Country | O1: Location | P1: Languages | Q1: Publications | R1: Honors And Awards | S1: Patents | T1: Volunteer and Awards | U1: License and Certifications | V1: Interests | W1: Work Experience | X1: Education | Y1: LinkedIn Summary | Z1: Headline
